{
  "slug": "a-meal-makes-her-forgett.vv836",
  "title": "A Meal Makes Her Forget",
  "cover": "https://static.mfcdn.nl/bab8/i/b/bb/bb7795b1568b55ec38271090c0939560@100.jpg",
  "description": "A Meal Makes Her Forget manga, read all chapters here, the latest chapter 2 is available. Read A Meal Makes Her Forget raw, multiple language. READ NOW!!",
  "status": "Releasing",
  "genres": [
    "Action",
    "Adventure",
    "Avant Garde",
    "Boys Love",
    "Comedy",
    "Demons",
    "Drama",
    "Ecchi",
    "Fantasy",
    "Girls Love",
    "Gourmet",
    "Harem",
    "Horror",
    "Isekai",
    "Iyashikei",
    "Josei",
    "Kids",
    "Magic",
    "Mahou Shoujo",
    "Martial Arts",
    "Mecha",
    "Military",
    "Music",
    "Mystery",
    "Parody",
    "Psychological",
    "Reverse Harem",
    "Romance",
    "School",
    "Sci-Fi",
    "Seinen",
    "Shoujo",
    "Shounen",
    "Slice of Life",
    "Space",
    "Sports",
    "Super Power",
    "Supernatural",
    "Suspense",
    "Thriller",
    "Vampire",
    "Comedy",
    "Gourmet",
    "Seinen",
    "Slice of Life"
  ],
  "chapters": [
    {
      "number": "2",
      "title": "Vol 1 -  Chap 2",
      "url": "https://mangafire.to/read/a-meal-makes-her-forgett.vv836/en/chapter-2"
    },
    {
      "number": "1",
      "title": "Vol 1 -  Chap 1",
      "url": "https://mangafire.to/read/a-meal-makes-her-forgett.vv836/en/chapter-1"
    }
  ],
  "fetched_at": "2026-04-27T08:07:33Z"
}