{
  "slug": "aisou-hito-sex-friendd.l37yz",
  "title": "Amiable Man - Sex Friend",
  "cover": "https://static.mfcdn.nl/d4e7/i/5/5f/5f568c089fc157f4768060d9ecd97ada@100.jpg",
  "description": "Amiable Man - Sex Friend manga, read all chapters here, the latest chapter 4 is available. Read Amiable Man - Sex Friend raw, multiple language. READ NOW!!",
  "status": "Completed",
  "genres": [
    "Action",
    "Adventure",
    "Avant Garde",
    "Boys Love",
    "Comedy",
    "Demons",
    "Drama",
    "Ecchi",
    "Fantasy",
    "Girls Love",
    "Gourmet",
    "Harem",
    "Horror",
    "Isekai",
    "Iyashikei",
    "Josei",
    "Kids",
    "Magic",
    "Mahou Shoujo",
    "Martial Arts",
    "Mecha",
    "Military",
    "Music",
    "Mystery",
    "Parody",
    "Psychological",
    "Reverse Harem",
    "Romance",
    "School",
    "Sci-Fi",
    "Seinen",
    "Shoujo",
    "Shounen",
    "Slice of Life",
    "Space",
    "Sports",
    "Super Power",
    "Supernatural",
    "Suspense",
    "Thriller",
    "Vampire",
    "Ecchi",
    "Romance",
    "Shoujo"
  ],
  "chapters": [
    {
      "number": "4",
      "title": "Chap 4",
      "url": "https://mangafire.to/read/aisou-hito-sex-friendd.l37yz/en/chapter-4"
    },
    {
      "number": "3",
      "title": "Chap 3",
      "url": "https://mangafire.to/read/aisou-hito-sex-friendd.l37yz/en/chapter-3"
    },
    {
      "number": "2",
      "title": "Chap 2",
      "url": "https://mangafire.to/read/aisou-hito-sex-friendd.l37yz/en/chapter-2"
    },
    {
      "number": "1",
      "title": "Chap 1",
      "url": "https://mangafire.to/read/aisou-hito-sex-friendd.l37yz/en/chapter-1"
    }
  ],
  "fetched_at": "2026-04-27T07:24:58Z"
}