{
  "slug": "chuan-cheng-alpha-da-lao-de-jin-si-da-e.qzzlv",
  "title": "Transmigrated as the Alpha Boss' Golden Goose",
  "cover": "https://static.mfcdn.nl/eb19/i/0/0e/0e2422ee85a74121b551d2b65d493afe@100.jpg",
  "description": "Transmigrated as the Alpha Boss' Golden Goose manga, read all chapters here, the latest chapter 4 is available. Read Transmigrated as the Alpha Boss' Golden Goose raw, multiple language. READ NOW!!",
  "status": "Releasing",
  "genres": [
    "Action",
    "Adventure",
    "Avant Garde",
    "Boys Love",
    "Comedy",
    "Demons",
    "Drama",
    "Ecchi",
    "Fantasy",
    "Girls Love",
    "Gourmet",
    "Harem",
    "Horror",
    "Isekai",
    "Iyashikei",
    "Josei",
    "Kids",
    "Magic",
    "Mahou Shoujo",
    "Martial Arts",
    "Mecha",
    "Military",
    "Music",
    "Mystery",
    "Parody",
    "Psychological",
    "Reverse Harem",
    "Romance",
    "School",
    "Sci-Fi",
    "Seinen",
    "Shoujo",
    "Shounen",
    "Slice of Life",
    "Space",
    "Sports",
    "Super Power",
    "Supernatural",
    "Suspense",
    "Thriller",
    "Vampire",
    "Drama",
    "Romance",
    "Fantasy"
  ],
  "chapters": [
    {
      "number": "4",
      "title": "Chap 4",
      "url": "https://mangafire.to/read/chuan-cheng-alpha-da-lao-de-jin-si-da-e.qzzlv/en/chapter-4"
    },
    {
      "number": "3",
      "title": "Chap 3",
      "url": "https://mangafire.to/read/chuan-cheng-alpha-da-lao-de-jin-si-da-e.qzzlv/en/chapter-3"
    },
    {
      "number": "2",
      "title": "Chap 2",
      "url": "https://mangafire.to/read/chuan-cheng-alpha-da-lao-de-jin-si-da-e.qzzlv/en/chapter-2"
    },
    {
      "number": "1",
      "title": "Chap 1",
      "url": "https://mangafire.to/read/chuan-cheng-alpha-da-lao-de-jin-si-da-e.qzzlv/en/chapter-1"
    },
    {
      "number": "0",
      "title": "Chap 0",
      "url": "https://mangafire.to/read/chuan-cheng-alpha-da-lao-de-jin-si-da-e.qzzlv/en/chapter-0"
    }
  ],
  "fetched_at": "2026-05-01T07:59:01Z"
}