{
  "slug": "dragon-ball-super.8235y",
  "title": "Dragon Ball Super",
  "cover": "https://static.mfcdn.nl/2f64/i/3/30/40825b829a241fd494d765e2baa4f227@100.jpg",
  "description": "Dragon Ball Super manga, read all chapters here, the latest chapter 517 is available. Read Dragon Ball Super raw, multiple language. READ NOW!!",
  "status": "Releasing",
  "genres": [
    "Action",
    "Adventure",
    "Avant Garde",
    "Boys Love",
    "Comedy",
    "Demons",
    "Drama",
    "Ecchi",
    "Fantasy",
    "Girls Love",
    "Gourmet",
    "Harem",
    "Horror",
    "Isekai",
    "Iyashikei",
    "Josei",
    "Kids",
    "Magic",
    "Mahou Shoujo",
    "Martial Arts",
    "Mecha",
    "Military",
    "Music",
    "Mystery",
    "Parody",
    "Psychological",
    "Reverse Harem",
    "Romance",
    "School",
    "Sci-Fi",
    "Seinen",
    "Shoujo",
    "Shounen",
    "Slice of Life",
    "Space",
    "Sports",
    "Super Power",
    "Supernatural",
    "Suspense",
    "Thriller",
    "Vampire",
    "Action",
    "Comedy",
    "Drama",
    "Sci-Fi",
    "Shounen",
    "Adventure",
    "Fantasy"
  ],
  "chapters": [
    {
      "number": "517",
      "title": "Vol 0 -  Chap 517",
      "url": "https://mangafire.to/read/dragon-ball-super.8235y/en/chapter-517"
    },
    {
      "number": "516",
      "title": "Vol 0 -  Chap 516",
      "url": "https://mangafire.to/read/dragon-ball-super.8235y/en/chapter-516"
    },
    {
      "number": "515",
      "title": "Vol 0 -  Chap 515",
      "url": "https://mangafire.to/read/dragon-ball-super.8235y/en/chapter-515"
    },
    {
      "number": "514",
      "title": "Vol 0 -  Chap 514",
      "url": "https://mangafire.to/read/dragon-ball-super.8235y/en/chapter-514"
    },
    {
      "number": "513",
      "title": "Vol 0 -  Chap 513",
      "url": "https://mangafire.to/read/dragon-ball-super.8235y/en/chapter-513"
    },
    {
      "number": "512",
      "title": "Vol 0 -  Chap 512",
      "url": "https://mangafire.to/read/dragon-ball-super.8235y/en/chapter-512"
    },
    {
      "number": "510",
      "title": "Vol 0 -  Chap 510",
      "url": "https://mangafire.to/read/dragon-ball-super.8235y/en/chapter-510"
    },
    {
      "number": "509",
      "title": "Vol 0 -  Chap 509",
      "url": "https://mangafire.to/read/dragon-ball-super.8235y/en/chapter-509"
    },
    {
      "number": "508",
      "title": "Vol 0 -  Chap 508",
      "url": "https://mangafire.to/read/dragon-ball-super.8235y/en/chapter-508"
    },
    {
      "number": "507",
      "title": "Vol 0 -  Chap 507",
      "url": "https://mangafire.to/read/dragon-ball-super.8235y/en/chapter-507"
    },
    {
      "number": "506",
      "title": "Vol 0 -  Chap 506",
      "url": "https://mangafire.to/read/dragon-ball-super.8235y/en/chapter-506"
    },
    {
      "number": "505",
      "title": "Vol 0 -  Chap 505",
      "url": "https://mangafire.to/read/dragon-ball-super.8235y/en/chapter-505"
    },
    {
      "number": "504",
      "title": "Vol 0 -  Chap 504",
      "url": "https://mangafire.to/read/dragon-ball-super.8235y/en/chapter-504"
    },
    {
      "number": "503",
      "title": "Vol 0 -  Chap 503",
      "url": "https://mangafire.to/read/dragon-ball-super.8235y/en/chapter-503"
    },
    {
      "number": "502",
      "title": "Vol 0 -  Chap 502",
      "url": "https://mangafire.to/read/dragon-ball-super.8235y/en/chapter-502"
    },
    {
      "number": "501",
      "title": "Vol 0 -  Chap 501",
      "url": "https://mangafire.to/read/dragon-ball-super.8235y/en/chapter-501"
    },
    {
      "number": "499",
      "title": "Vol 0 -  Chap 499",
      "url": "https://mangafire.to/read/dragon-ball-super.8235y/en/chapter-499"
    },
    {
      "number": "498",
      "title": "Vol 0 -  Chap 498",
      "url": "https://mangafire.to/read/dragon-ball-super.8235y/en/chapter-498"
    },
    {
      "number": "497",
      "title": "Vol 0 -  Chap 497",
      "url": "https://mangafire.to/read/dragon-ball-super.8235y/en/chapter-497"
    },
    {
      "number": "496",
      "title": "Vol 0 -  Chap 496",
      "url": "https://mangafire.to/read/dragon-ball-super.8235y/en/chapter-496"
    },
    {
      "number": "495",
      "title": "Vol 0 -  Chap 495",
      "url": "https://mangafire.to/read/dragon-ball-super.8235y/en/chapter-495"
    },
    {
      "number": "494",
      "title": "Vol 0 -  Chap 494",
      "url": "https://mangafire.to/read/dragon-ball-super.8235y/en/chapter-494"
    },
    {
      "number": "493",
      "title": "Vol 0 -  Chap 493",
      "url": "https://mangafire.to/read/dragon-ball-super.8235y/en/chapter-493"
    },
    {
      "number": "492",
      "title": "Vol 0 -  Chap 492",
      "url": "https://mangafire.to/read/dragon-ball-super.8235y/en/chapter-492"
    },
    {
      "number": "491",
      "title": "Vol 0 -  Chap 491",
      "url": "https://mangafire.to/read/dragon-ball-super.8235y/en/chapter-491"
    },
    {
      "number": "488",
      "title": "Vol 0 -  Chap 488",
      "url": "https://mangafire.to/read/dragon-ball-super.8235y/en/chapter-488"
    },
    {
      "number": "487",
      "title": "Vol 0 -  Chap 487",
      "url": "https://mangafire.to/read/dragon-ball-super.8235y/en/chapter-487"
    },
    {
      "number": "486",
      "title": "Vol 0 -  Chap 486",
      "url": "https://mangafire.to/read/dragon-ball-super.8235y/en/chapter-486"
    },
    {
      "number": "485",
      "title": "Vol 0 -  Chap 485",
      "url": "https://mangafire.to/read/dragon-ball-super.8235y/en/chapter-485"
    },
    {
      "number": "484",
      "title": "Vol 0 -  Chap 484",
      "url": "https://mangafire.to/read/dragon-ball-super.8235y/en/chapter-484"
    },
    {
      "number": "483",
      "title": "Vol 0 -  Chap 483",
      "url": "https://mangafire.to/read/dragon-ball-super.8235y/en/chapter-483"
    },
    {
      "number": "482",
      "title": "Vol 0 -  Chap 482",
      "url": "https://mangafire.to/read/dragon-ball-super.8235y/en/chapter-482"
    },
    {
      "number": "481",
      "title": "Vol 0 -  Chap 481",
      "url": "https://mangafire.to/read/dragon-ball-super.8235y/en/chapter-481"
    },
    {
      "number": "480",
      "title": "Vol 0 -  Chap 480",
      "url": "https://mangafire.to/read/dragon-ball-super.8235y/en/chapter-480"
    },
    {
      "number": "479",
      "title": "Vol 0 -  Chap 479",
      "url": "https://mangafire.to/read/dragon-ball-super.8235y/en/chapter-479"
    },
    {
      "number": "477",
      "title": "Vol 0 -  Chap 477",
      "url": "https://mangafire.to/read/dragon-ball-super.8235y/en/chapter-477"
    },
    {
      "number": "476",
      "title": "Vol 0 -  Chap 476",
      "url": "https://mangafire.to/read/dragon-ball-super.8235y/en/chapter-476"
    },
    {
      "number": "475",
      "title": "Vol 0 -  Chap 475",
      "url": "https://mangafire.to/read/dragon-ball-super.8235y/en/chapter-475"
    },
    {
      "number": "474",
      "title": "Vol 0 -  Chap 474",
      "url": "https://mangafire.to/read/dragon-ball-super.8235y/en/chapter-474"
    },
    {
      "number": "473",
      "title": "Vol 0 -  Chap 473",
      "url": "https://mangafire.to/read/dragon-ball-super.8235y/en/chapter-473"
    },
    {
      "number": "471",
      "title": "Vol 0 -  Chap 471",
      "url": "https://mangafire.to/read/dragon-ball-super.8235y/en/chapter-471"
    },
    {
      "number": "470",
      "title": "Vol 0 -  Chap 470",
      "url": "https://mangafire.to/read/dragon-ball-super.8235y/en/chapter-470"
    },
    {
      "number": "468",
      "title": "Vol 0 -  Chap 468",
      "url": "https://mangafire.to/read/dragon-ball-super.8235y/en/chapter-468"
    },
    {
      "number": "467",
      "title": "Vol 0 -  Chap 467",
      "url": "https://mangafire.to/read/dragon-ball-super.8235y/en/chapter-467"
    },
    {
      "number": "466",
      "title": "Vol 0 -  Chap 466",
      "url": "https://mangafire.to/read/dragon-ball-super.8235y/en/chapter-466"
    },
    {
      "number": "465",
      "title": "Vol 0 -  Chap 465",
      "url": "https://mangafire.to/read/dragon-ball-super.8235y/en/chapter-465"
    },
    {
      "number": "464",
      "title": "Vol 0 -  Chap 464",
      "url": "https://mangafire.to/read/dragon-ball-super.8235y/en/chapter-464"
    },
    {
      "number": "463",
      "title": "Vol 0 -  Chap 463",
      "url": "https://mangafire.to/read/dragon-ball-super.8235y/en/chapter-463"
    },
    {
      "number": "462",
      "title": "Vol 0 -  Chap 462",
      "url": "https://mangafire.to/read/dragon-ball-super.8235y/en/chapter-462"
    },
    {
      "number": "461",
      "title": "Vol 0 -  Chap 461",
      "url": "https://mangafire.to/read/dragon-ball-super.8235y/en/chapter-461"
    },
    {
      "number": "458",
      "title": "Vol 0 -  Chap 458",
      "url": "https://mangafire.to/read/dragon-ball-super.8235y/en/chapter-458"
    },
    {
      "number": "457",
      "title": "Vol 0 -  Chap 457",
      "url": "https://mangafire.to/read/dragon-ball-super.8235y/en/chapter-457"
    },
    {
      "number": "456",
      "title": "Vol 0 -  Chap 456",
      "url": "https://mangafire.to/read/dragon-ball-super.8235y/en/chapter-456"
    },
    {
      "number": "455",
      "title": "Vol 0 -  Chap 455",
      "url": "https://mangafire.to/read/dragon-ball-super.8235y/en/chapter-455"
    },
    {
      "number": "454",
      "title": "Vol 0 -  Chap 454",
      "url": "https://mangafire.to/read/dragon-ball-super.8235y/en/chapter-454"
    },
    {
      "number": "453",
      "title": "Vol 0 -  Chap 453",
      "url": "https://mangafire.to/read/dragon-ball-super.8235y/en/chapter-453"
    },
    {
      "number": "452",
      "title": "Vol 0 -  Chap 452",
      "url": "https://mangafire.to/read/dragon-ball-super.8235y/en/chapter-452"
    },
    {
      "number": "451",
      "title": "Vol 0 -  Chap 451",
      "url": "https://mangafire.to/read/dragon-ball-super.8235y/en/chapter-451"
    },
    {
      "number": "450",
      "title": "Vol 0 -  Chap 450",
      "url": "https://mangafire.to/read/dragon-ball-super.8235y/en/chapter-450"
    },
    {
      "number": "449",
      "title": "Vol 0 -  Chap 449",
      "url": "https://mangafire.to/read/dragon-ball-super.8235y/en/chapter-449"
    },
    {
      "number": "448",
      "title": "Vol 0 -  Chap 448",
      "url": "https://mangafire.to/read/dragon-ball-super.8235y/en/chapter-448"
    },
    {
      "number": "447",
      "title": "Vol 0 -  Chap 447",
      "url": "https://mangafire.to/read/dragon-ball-super.8235y/en/chapter-447"
    },
    {
      "number": "446",
      "title": "Vol 0 -  Chap 446",
      "url": "https://mangafire.to/read/dragon-ball-super.8235y/en/chapter-446"
    },
    {
      "number": "445",
      "title": "Vol 0 -  Chap 445",
      "url": "https://mangafire.to/read/dragon-ball-super.8235y/en/chapter-445"
    },
    {
      "number": "444",
      "title": "Vol 0 -  Chap 444",
      "url": "https://mangafire.to/read/dragon-ball-super.8235y/en/chapter-444"
    },
    {
      "number": "443",
      "title": "Vol 0 -  Chap 443",
      "url": "https://mangafire.to/read/dragon-ball-super.8235y/en/chapter-443"
    },
    {
      "number": "442",
      "title": "Vol 0 -  Chap 442",
      "url": "https://mangafire.to/read/dragon-ball-super.8235y/en/chapter-442"
    },
    {
      "number": "441",
      "title": "Vol 0 -  Chap 441",
      "url": "https://mangafire.to/read/dragon-ball-super.8235y/en/chapter-441"
    },
    {
      "number": "439",
      "title": "Vol 0 -  Chap 439",
      "url": "https://mangafire.to/read/dragon-ball-super.8235y/en/chapter-439"
    },
    {
      "number": "438",
      "title": "Vol 0 -  Chap 438",
      "url": "https://mangafire.to/read/dragon-ball-super.8235y/en/chapter-438"
    },
    {
      "number": "437",
      "title": "Vol 0 -  Chap 437",
      "url": "https://mangafire.to/read/dragon-ball-super.8235y/en/chapter-437"
    },
    {
      "number": "436",
      "title": "Vol 0 -  Chap 436",
      "url": "https://mangafire.to/read/dragon-ball-super.8235y/en/chapter-436"
    },
    {
      "number": "434",
      "title": "Vol 0 -  Chap 434",
      "url": "https://mangafire.to/read/dragon-ball-super.8235y/en/chapter-434"
    },
    {
      "number": "433",
      "title": "Vol 0 -  Chap 433",
      "url": "https://mangafire.to/read/dragon-ball-super.8235y/en/chapter-433"
    },
    {
      "number": "432",
      "title": "Vol 0 -  Chap 432",
      "url": "https://mangafire.to/read/dragon-ball-super.8235y/en/chapter-432"
    },
    {
      "number": "431",
      "title": "Vol 0 -  Chap 431",
      "url": "https://mangafire.to/read/dragon-ball-super.8235y/en/chapter-431"
    },
    {
      "number": "430",
      "title": "Vol 0 -  Chap 430",
      "url": "https://mangafire.to/read/dragon-ball-super.8235y/en/chapter-430"
    },
    {
      "number": "428",
      "title": "Vol 0 -  Chap 428",
      "url": "https://mangafire.to/read/dragon-ball-super.8235y/en/chapter-428"
    },
    {
      "number": "427",
      "title": "Vol 0 -  Chap 427",
      "url": "https://mangafire.to/read/dragon-ball-super.8235y/en/chapter-427"
    },
    {
      "number": "426",
      "title": "Vol 0 -  Chap 426",
      "url": "https://mangafire.to/read/dragon-ball-super.8235y/en/chapter-426"
    },
    {
      "number": "424",
      "title": "Vol 0 -  Chap 424",
      "url": "https://mangafire.to/read/dragon-ball-super.8235y/en/chapter-424"
    },
    {
      "number": "423",
      "title": "Vol 0 -  Chap 423",
      "url": "https://mangafire.to/read/dragon-ball-super.8235y/en/chapter-423"
    },
    {
      "number": "422",
      "title": "Vol 0 -  Chap 422",
      "url": "https://mangafire.to/read/dragon-ball-super.8235y/en/chapter-422"
    },
    {
      "number": "421",
      "title": "Vol 0 -  Chap 421",
      "url": "https://mangafire.to/read/dragon-ball-super.8235y/en/chapter-421"
    },
    {
      "number": "420",
      "title": "Vol 0 -  Chap 420",
      "url": "https://mangafire.to/read/dragon-ball-super.8235y/en/chapter-420"
    },
    {
      "number": "419",
      "title": "Vol 0 -  Chap 419",
      "url": "https://mangafire.to/read/dragon-ball-super.8235y/en/chapter-419"
    },
    {
      "number": "418",
      "title": "Vol 0 -  Chap 418",
      "url": "https://mangafire.to/read/dragon-ball-super.8235y/en/chapter-418"
    },
    {
      "number": "417",
      "title": "Vol 0 -  Chap 417",
      "url": "https://mangafire.to/read/dragon-ball-super.8235y/en/chapter-417"
    },
    {
      "number": "416",
      "title": "Vol 0 -  Chap 416",
      "url": "https://mangafire.to/read/dragon-ball-super.8235y/en/chapter-416"
    },
    {
      "number": "415",
      "title": "Vol 0 -  Chap 415",
      "url": "https://mangafire.to/read/dragon-ball-super.8235y/en/chapter-415"
    },
    {
      "number": "414",
      "title": "Vol 0 -  Chap 414",
      "url": "https://mangafire.to/read/dragon-ball-super.8235y/en/chapter-414"
    },
    {
      "number": "413",
      "title": "Vol 0 -  Chap 413",
      "url": "https://mangafire.to/read/dragon-ball-super.8235y/en/chapter-413"
    },
    {
      "number": "411",
      "title": "Vol 0 -  Chap 411",
      "url": "https://mangafire.to/read/dragon-ball-super.8235y/en/chapter-411"
    },
    {
      "number": "409",
      "title": "Vol 0 -  Chap 409",
      "url": "https://mangafire.to/read/dragon-ball-super.8235y/en/chapter-409"
    },
    {
      "number": "408",
      "title": "Vol 0 -  Chap 408",
      "url": "https://mangafire.to/read/dragon-ball-super.8235y/en/chapter-408"
    },
    {
      "number": "406",
      "title": "Vol 0 -  Chap 406",
      "url": "https://mangafire.to/read/dragon-ball-super.8235y/en/chapter-406"
    },
    {
      "number": "404",
      "title": "Vol 0 -  Chap 404",
      "url": "https://mangafire.to/read/dragon-ball-super.8235y/en/chapter-404"
    },
    {
      "number": "403",
      "title": "Vol 0 -  Chap 403",
      "url": "https://mangafire.to/read/dragon-ball-super.8235y/en/chapter-403"
    },
    {
      "number": "402",
      "title": "Vol 0 -  Chap 402",
      "url": "https://mangafire.to/read/dragon-ball-super.8235y/en/chapter-402"
    },
    {
      "number": "401",
      "title": "Vol 0 -  Chap 401",
      "url": "https://mangafire.to/read/dragon-ball-super.8235y/en/chapter-401"
    },
    {
      "number": "399",
      "title": "Vol 0 -  Chap 399",
      "url": "https://mangafire.to/read/dragon-ball-super.8235y/en/chapter-399"
    },
    {
      "number": "398",
      "title": "Vol 0 -  Chap 398",
      "url": "https://mangafire.to/read/dragon-ball-super.8235y/en/chapter-398"
    },
    {
      "number": "397",
      "title": "Vol 0 -  Chap 397",
      "url": "https://mangafire.to/read/dragon-ball-super.8235y/en/chapter-397"
    },
    {
      "number": "396",
      "title": "Vol 0 -  Chap 396",
      "url": "https://mangafire.to/read/dragon-ball-super.8235y/en/chapter-396"
    },
    {
      "number": "395",
      "title": "Vol 0 -  Chap 395",
      "url": "https://mangafire.to/read/dragon-ball-super.8235y/en/chapter-395"
    },
    {
      "number": "392",
      "title": "Vol 0 -  Chap 392",
      "url": "https://mangafire.to/read/dragon-ball-super.8235y/en/chapter-392"
    },
    {
      "number": "391",
      "title": "Vol 0 -  Chap 391",
      "url": "https://mangafire.to/read/dragon-ball-super.8235y/en/chapter-391"
    },
    {
      "number": "389",
      "title": "Vol 0 -  Chap 389",
      "url": "https://mangafire.to/read/dragon-ball-super.8235y/en/chapter-389"
    },
    {
      "number": "388",
      "title": "Vol 0 -  Chap 388",
      "url": "https://mangafire.to/read/dragon-ball-super.8235y/en/chapter-388"
    },
    {
      "number": "387",
      "title": "Vol 0 -  Chap 387",
      "url": "https://mangafire.to/read/dragon-ball-super.8235y/en/chapter-387"
    },
    {
      "number": "386",
      "title": "Vol 0 -  Chap 386",
      "url": "https://mangafire.to/read/dragon-ball-super.8235y/en/chapter-386"
    },
    {
      "number": "385",
      "title": "Vol 0 -  Chap 385",
      "url": "https://mangafire.to/read/dragon-ball-super.8235y/en/chapter-385"
    },
    {
      "number": "384",
      "title": "Vol 0 -  Chap 384",
      "url": "https://mangafire.to/read/dragon-ball-super.8235y/en/chapter-384"
    },
    {
      "number": "383",
      "title": "Vol 0 -  Chap 383",
      "url": "https://mangafire.to/read/dragon-ball-super.8235y/en/chapter-383"
    },
    {
      "number": "382",
      "title": "Vol 0 -  Chap 382",
      "url": "https://mangafire.to/read/dragon-ball-super.8235y/en/chapter-382"
    },
    {
      "number": "381",
      "title": "Vol 0 -  Chap 381",
      "url": "https://mangafire.to/read/dragon-ball-super.8235y/en/chapter-381"
    },
    {
      "number": "380",
      "title": "Vol 0 -  Chap 380",
      "url": "https://mangafire.to/read/dragon-ball-super.8235y/en/chapter-380"
    },
    {
      "number": "379",
      "title": "Vol 0 -  Chap 379",
      "url": "https://mangafire.to/read/dragon-ball-super.8235y/en/chapter-379"
    },
    {
      "number": "378",
      "title": "Vol 0 -  Chap 378",
      "url": "https://mangafire.to/read/dragon-ball-super.8235y/en/chapter-378"
    },
    {
      "number": "377",
      "title": "Vol 0 -  Chap 377",
      "url": "https://mangafire.to/read/dragon-ball-super.8235y/en/chapter-377"
    },
    {
      "number": "376",
      "title": "Vol 0 -  Chap 376",
      "url": "https://mangafire.to/read/dragon-ball-super.8235y/en/chapter-376"
    },
    {
      "number": "375",
      "title": "Vol 0 -  Chap 375",
      "url": "https://mangafire.to/read/dragon-ball-super.8235y/en/chapter-375"
    },
    {
      "number": "374",
      "title": "Vol 0 -  Chap 374",
      "url": "https://mangafire.to/read/dragon-ball-super.8235y/en/chapter-374"
    },
    {
      "number": "372",
      "title": "Vol 0 -  Chap 372",
      "url": "https://mangafire.to/read/dragon-ball-super.8235y/en/chapter-372"
    },
    {
      "number": "371",
      "title": "Vol 0 -  Chap 371",
      "url": "https://mangafire.to/read/dragon-ball-super.8235y/en/chapter-371"
    },
    {
      "number": "370",
      "title": "Vol 0 -  Chap 370",
      "url": "https://mangafire.to/read/dragon-ball-super.8235y/en/chapter-370"
    },
    {
      "number": "369",
      "title": "Vol 0 -  Chap 369",
      "url": "https://mangafire.to/read/dragon-ball-super.8235y/en/chapter-369"
    },
    {
      "number": "368",
      "title": "Vol 0 -  Chap 368",
      "url": "https://mangafire.to/read/dragon-ball-super.8235y/en/chapter-368"
    },
    {
      "number": "367",
      "title": "Vol 0 -  Chap 367",
      "url": "https://mangafire.to/read/dragon-ball-super.8235y/en/chapter-367"
    },
    {
      "number": "366",
      "title": "Vol 0 -  Chap 366",
      "url": "https://mangafire.to/read/dragon-ball-super.8235y/en/chapter-366"
    },
    {
      "number": "364",
      "title": "Vol 0 -  Chap 364",
      "url": "https://mangafire.to/read/dragon-ball-super.8235y/en/chapter-364"
    },
    {
      "number": "363",
      "title": "Vol 0 -  Chap 363",
      "url": "https://mangafire.to/read/dragon-ball-super.8235y/en/chapter-363"
    },
    {
      "number": "362",
      "title": "Vol 0 -  Chap 362",
      "url": "https://mangafire.to/read/dragon-ball-super.8235y/en/chapter-362"
    },
    {
      "number": "361",
      "title": "Vol 0 -  Chap 361",
      "url": "https://mangafire.to/read/dragon-ball-super.8235y/en/chapter-361"
    },
    {
      "number": "360",
      "title": "Vol 0 -  Chap 360",
      "url": "https://mangafire.to/read/dragon-ball-super.8235y/en/chapter-360"
    },
    {
      "number": "359",
      "title": "Vol 0 -  Chap 359",
      "url": "https://mangafire.to/read/dragon-ball-super.8235y/en/chapter-359"
    },
    {
      "number": "358",
      "title": "Vol 0 -  Chap 358",
      "url": "https://mangafire.to/read/dragon-ball-super.8235y/en/chapter-358"
    },
    {
      "number": "357",
      "title": "Vol 0 -  Chap 357",
      "url": "https://mangafire.to/read/dragon-ball-super.8235y/en/chapter-357"
    },
    {
      "number": "356",
      "title": "Vol 0 -  Chap 356",
      "url": "https://mangafire.to/read/dragon-ball-super.8235y/en/chapter-356"
    },
    {
      "number": "355",
      "title": "Vol 0 -  Chap 355",
      "url": "https://mangafire.to/read/dragon-ball-super.8235y/en/chapter-355"
    },
    {
      "number": "354",
      "title": "Vol 0 -  Chap 354",
      "url": "https://mangafire.to/read/dragon-ball-super.8235y/en/chapter-354"
    },
    {
      "number": "353",
      "title": "Vol 0 -  Chap 353",
      "url": "https://mangafire.to/read/dragon-ball-super.8235y/en/chapter-353"
    },
    {
      "number": "352",
      "title": "Vol 0 -  Chap 352",
      "url": "https://mangafire.to/read/dragon-ball-super.8235y/en/chapter-352"
    },
    {
      "number": "351",
      "title": "Vol 0 -  Chap 351",
      "url": "https://mangafire.to/read/dragon-ball-super.8235y/en/chapter-351"
    },
    {
      "number": "350",
      "title": "Vol 0 -  Chap 350",
      "url": "https://mangafire.to/read/dragon-ball-super.8235y/en/chapter-350"
    },
    {
      "number": "349",
      "title": "Vol 0 -  Chap 349",
      "url": "https://mangafire.to/read/dragon-ball-super.8235y/en/chapter-349"
    },
    {
      "number": "348",
      "title": "Vol 0 -  Chap 348",
      "url": "https://mangafire.to/read/dragon-ball-super.8235y/en/chapter-348"
    },
    {
      "number": "346",
      "title": "Vol 0 -  Chap 346",
      "url": "https://mangafire.to/read/dragon-ball-super.8235y/en/chapter-346"
    },
    {
      "number": "345",
      "title": "Vol 0 -  Chap 345",
      "url": "https://mangafire.to/read/dragon-ball-super.8235y/en/chapter-345"
    },
    {
      "number": "344",
      "title": "Vol 0 -  Chap 344",
      "url": "https://mangafire.to/read/dragon-ball-super.8235y/en/chapter-344"
    },
    {
      "number": "343",
      "title": "Vol 0 -  Chap 343",
      "url": "https://mangafire.to/read/dragon-ball-super.8235y/en/chapter-343"
    },
    {
      "number": "342",
      "title": "Vol 0 -  Chap 342",
      "url": "https://mangafire.to/read/dragon-ball-super.8235y/en/chapter-342"
    },
    {
      "number": "341",
      "title": "Vol 0 -  Chap 341",
      "url": "https://mangafire.to/read/dragon-ball-super.8235y/en/chapter-341"
    },
    {
      "number": "339",
      "title": "Vol 0 -  Chap 339",
      "url": "https://mangafire.to/read/dragon-ball-super.8235y/en/chapter-339"
    },
    {
      "number": "337",
      "title": "Vol 0 -  Chap 337",
      "url": "https://mangafire.to/read/dragon-ball-super.8235y/en/chapter-337"
    },
    {
      "number": "336",
      "title": "Vol 0 -  Chap 336",
      "url": "https://mangafire.to/read/dragon-ball-super.8235y/en/chapter-336"
    },
    {
      "number": "335",
      "title": "Vol 0 -  Chap 335",
      "url": "https://mangafire.to/read/dragon-ball-super.8235y/en/chapter-335"
    },
    {
      "number": "334",
      "title": "Vol 0 -  Chap 334",
      "url": "https://mangafire.to/read/dragon-ball-super.8235y/en/chapter-334"
    },
    {
      "number": "333",
      "title": "Vol 0 -  Chap 333",
      "url": "https://mangafire.to/read/dragon-ball-super.8235y/en/chapter-333"
    },
    {
      "number": "332",
      "title": "Vol 0 -  Chap 332",
      "url": "https://mangafire.to/read/dragon-ball-super.8235y/en/chapter-332"
    },
    {
      "number": "331",
      "title": "Vol 0 -  Chap 331",
      "url": "https://mangafire.to/read/dragon-ball-super.8235y/en/chapter-331"
    },
    {
      "number": "330",
      "title": "Vol 0 -  Chap 330",
      "url": "https://mangafire.to/read/dragon-ball-super.8235y/en/chapter-330"
    },
    {
      "number": "329",
      "title": "Vol 0 -  Chap 329",
      "url": "https://mangafire.to/read/dragon-ball-super.8235y/en/chapter-329"
    },
    {
      "number": "327",
      "title": "Vol 0 -  Chap 327",
      "url": "https://mangafire.to/read/dragon-ball-super.8235y/en/chapter-327"
    },
    {
      "number": "326",
      "title": "Vol 0 -  Chap 326",
      "url": "https://mangafire.to/read/dragon-ball-super.8235y/en/chapter-326"
    },
    {
      "number": "325",
      "title": "Vol 0 -  Chap 325",
      "url": "https://mangafire.to/read/dragon-ball-super.8235y/en/chapter-325"
    },
    {
      "number": "324",
      "title": "Vol 0 -  Chap 324",
      "url": "https://mangafire.to/read/dragon-ball-super.8235y/en/chapter-324"
    },
    {
      "number": "323",
      "title": "Vol 0 -  Chap 323",
      "url": "https://mangafire.to/read/dragon-ball-super.8235y/en/chapter-323"
    },
    {
      "number": "322",
      "title": "Vol 0 -  Chap 322",
      "url": "https://mangafire.to/read/dragon-ball-super.8235y/en/chapter-322"
    },
    {
      "number": "320",
      "title": "Vol 0 -  Chap 320",
      "url": "https://mangafire.to/read/dragon-ball-super.8235y/en/chapter-320"
    },
    {
      "number": "319",
      "title": "Vol 0 -  Chap 319",
      "url": "https://mangafire.to/read/dragon-ball-super.8235y/en/chapter-319"
    },
    {
      "number": "318",
      "title": "Vol 0 -  Chap 318",
      "url": "https://mangafire.to/read/dragon-ball-super.8235y/en/chapter-318"
    },
    {
      "number": "317",
      "title": "Vol 0 -  Chap 317",
      "url": "https://mangafire.to/read/dragon-ball-super.8235y/en/chapter-317"
    },
    {
      "number": "316",
      "title": "Vol 0 -  Chap 316",
      "url": "https://mangafire.to/read/dragon-ball-super.8235y/en/chapter-316"
    },
    {
      "number": "315",
      "title": "Vol 0 -  Chap 315",
      "url": "https://mangafire.to/read/dragon-ball-super.8235y/en/chapter-315"
    },
    {
      "number": "314",
      "title": "Vol 0 -  Chap 314",
      "url": "https://mangafire.to/read/dragon-ball-super.8235y/en/chapter-314"
    },
    {
      "number": "312",
      "title": "Vol 0 -  Chap 312",
      "url": "https://mangafire.to/read/dragon-ball-super.8235y/en/chapter-312"
    },
    {
      "number": "308",
      "title": "Vol 0 -  Chap 308",
      "url": "https://mangafire.to/read/dragon-ball-super.8235y/en/chapter-308"
    },
    {
      "number": "307",
      "title": "Vol 0 -  Chap 307",
      "url": "https://mangafire.to/read/dragon-ball-super.8235y/en/chapter-307"
    },
    {
      "number": "306",
      "title": "Vol 0 -  Chap 306",
      "url": "https://mangafire.to/read/dragon-ball-super.8235y/en/chapter-306"
    },
    {
      "number": "304",
      "title": "Vol 0 -  Chap 304",
      "url": "https://mangafire.to/read/dragon-ball-super.8235y/en/chapter-304"
    },
    {
      "number": "303",
      "title": "Vol 0 -  Chap 303",
      "url": "https://mangafire.to/read/dragon-ball-super.8235y/en/chapter-303"
    },
    {
      "number": "301",
      "title": "Vol 0 -  Chap 301",
      "url": "https://mangafire.to/read/dragon-ball-super.8235y/en/chapter-301"
    },
    {
      "number": "300",
      "title": "Vol 0 -  Chap 300",
      "url": "https://mangafire.to/read/dragon-ball-super.8235y/en/chapter-300"
    },
    {
      "number": "296",
      "title": "Vol 0 -  Chap 296",
      "url": "https://mangafire.to/read/dragon-ball-super.8235y/en/chapter-296"
    },
    {
      "number": "294",
      "title": "Vol 0 -  Chap 294",
      "url": "https://mangafire.to/read/dragon-ball-super.8235y/en/chapter-294"
    },
    {
      "number": "293",
      "title": "Vol 0 -  Chap 293",
      "url": "https://mangafire.to/read/dragon-ball-super.8235y/en/chapter-293"
    },
    {
      "number": "290",
      "title": "Vol 0 -  Chap 290",
      "url": "https://mangafire.to/read/dragon-ball-super.8235y/en/chapter-290"
    },
    {
      "number": "289",
      "title": "Vol 0 -  Chap 289",
      "url": "https://mangafire.to/read/dragon-ball-super.8235y/en/chapter-289"
    },
    {
      "number": "288",
      "title": "Vol 0 -  Chap 288",
      "url": "https://mangafire.to/read/dragon-ball-super.8235y/en/chapter-288"
    },
    {
      "number": "286",
      "title": "Vol 0 -  Chap 286",
      "url": "https://mangafire.to/read/dragon-ball-super.8235y/en/chapter-286"
    },
    {
      "number": "285",
      "title": "Vol 0 -  Chap 285",
      "url": "https://mangafire.to/read/dragon-ball-super.8235y/en/chapter-285"
    },
    {
      "number": "283",
      "title": "Vol 0 -  Chap 283",
      "url": "https://mangafire.to/read/dragon-ball-super.8235y/en/chapter-283"
    },
    {
      "number": "281",
      "title": "Vol 0 -  Chap 281",
      "url": "https://mangafire.to/read/dragon-ball-super.8235y/en/chapter-281"
    },
    {
      "number": "280",
      "title": "Vol 0 -  Chap 280",
      "url": "https://mangafire.to/read/dragon-ball-super.8235y/en/chapter-280"
    },
    {
      "number": "279",
      "title": "Vol 0 -  Chap 279",
      "url": "https://mangafire.to/read/dragon-ball-super.8235y/en/chapter-279"
    },
    {
      "number": "278",
      "title": "Vol 0 -  Chap 278",
      "url": "https://mangafire.to/read/dragon-ball-super.8235y/en/chapter-278"
    },
    {
      "number": "277",
      "title": "Vol 0 -  Chap 277",
      "url": "https://mangafire.to/read/dragon-ball-super.8235y/en/chapter-277"
    },
    {
      "number": "276",
      "title": "Vol 0 -  Chap 276",
      "url": "https://mangafire.to/read/dragon-ball-super.8235y/en/chapter-276"
    },
    {
      "number": "275",
      "title": "Vol 0 -  Chap 275",
      "url": "https://mangafire.to/read/dragon-ball-super.8235y/en/chapter-275"
    },
    {
      "number": "272",
      "title": "Vol 0 -  Chap 272",
      "url": "https://mangafire.to/read/dragon-ball-super.8235y/en/chapter-272"
    },
    {
      "number": "270",
      "title": "Vol 0 -  Chap 270",
      "url": "https://mangafire.to/read/dragon-ball-super.8235y/en/chapter-270"
    },
    {
      "number": "269",
      "title": "Vol 0 -  Chap 269",
      "url": "https://mangafire.to/read/dragon-ball-super.8235y/en/chapter-269"
    },
    {
      "number": "268",
      "title": "Vol 0 -  Chap 268",
      "url": "https://mangafire.to/read/dragon-ball-super.8235y/en/chapter-268"
    },
    {
      "number": "267",
      "title": "Vol 0 -  Chap 267",
      "url": "https://mangafire.to/read/dragon-ball-super.8235y/en/chapter-267"
    },
    {
      "number": "266",
      "title": "Vol 0 -  Chap 266",
      "url": "https://mangafire.to/read/dragon-ball-super.8235y/en/chapter-266"
    },
    {
      "number": "265",
      "title": "Vol 0 -  Chap 265",
      "url": "https://mangafire.to/read/dragon-ball-super.8235y/en/chapter-265"
    },
    {
      "number": "264",
      "title": "Vol 0 -  Chap 264",
      "url": "https://mangafire.to/read/dragon-ball-super.8235y/en/chapter-264"
    },
    {
      "number": "263",
      "title": "Vol 0 -  Chap 263",
      "url": "https://mangafire.to/read/dragon-ball-super.8235y/en/chapter-263"
    },
    {
      "number": "262",
      "title": "Vol 0 -  Chap 262",
      "url": "https://mangafire.to/read/dragon-ball-super.8235y/en/chapter-262"
    },
    {
      "number": "260",
      "title": "Vol 0 -  Chap 260",
      "url": "https://mangafire.to/read/dragon-ball-super.8235y/en/chapter-260"
    },
    {
      "number": "259",
      "title": "Vol 0 -  Chap 259",
      "url": "https://mangafire.to/read/dragon-ball-super.8235y/en/chapter-259"
    },
    {
      "number": "256",
      "title": "Vol 0 -  Chap 256",
      "url": "https://mangafire.to/read/dragon-ball-super.8235y/en/chapter-256"
    },
    {
      "number": "254",
      "title": "Vol 0 -  Chap 254",
      "url": "https://mangafire.to/read/dragon-ball-super.8235y/en/chapter-254"
    },
    {
      "number": "253",
      "title": "Vol 0 -  Chap 253",
      "url": "https://mangafire.to/read/dragon-ball-super.8235y/en/chapter-253"
    },
    {
      "number": "252",
      "title": "Vol 0 -  Chap 252",
      "url": "https://mangafire.to/read/dragon-ball-super.8235y/en/chapter-252"
    },
    {
      "number": "251",
      "title": "Vol 0 -  Chap 251",
      "url": "https://mangafire.to/read/dragon-ball-super.8235y/en/chapter-251"
    },
    {
      "number": "250",
      "title": "Vol 0 -  Chap 250",
      "url": "https://mangafire.to/read/dragon-ball-super.8235y/en/chapter-250"
    },
    {
      "number": "248",
      "title": "Vol 0 -  Chap 248",
      "url": "https://mangafire.to/read/dragon-ball-super.8235y/en/chapter-248"
    },
    {
      "number": "246",
      "title": "Vol 0 -  Chap 246",
      "url": "https://mangafire.to/read/dragon-ball-super.8235y/en/chapter-246"
    },
    {
      "number": "245",
      "title": "Vol 0 -  Chap 245",
      "url": "https://mangafire.to/read/dragon-ball-super.8235y/en/chapter-245"
    },
    {
      "number": "244",
      "title": "Vol 0 -  Chap 244",
      "url": "https://mangafire.to/read/dragon-ball-super.8235y/en/chapter-244"
    },
    {
      "number": "243",
      "title": "Vol 0 -  Chap 243",
      "url": "https://mangafire.to/read/dragon-ball-super.8235y/en/chapter-243"
    },
    {
      "number": "242",
      "title": "Vol 0 -  Chap 242",
      "url": "https://mangafire.to/read/dragon-ball-super.8235y/en/chapter-242"
    },
    {
      "number": "241",
      "title": "Vol 0 -  Chap 241",
      "url": "https://mangafire.to/read/dragon-ball-super.8235y/en/chapter-241"
    },
    {
      "number": "240",
      "title": "Vol 0 -  Chap 240",
      "url": "https://mangafire.to/read/dragon-ball-super.8235y/en/chapter-240"
    },
    {
      "number": "239",
      "title": "Vol 0 -  Chap 239",
      "url": "https://mangafire.to/read/dragon-ball-super.8235y/en/chapter-239"
    },
    {
      "number": "237",
      "title": "Vol 0 -  Chap 237",
      "url": "https://mangafire.to/read/dragon-ball-super.8235y/en/chapter-237"
    },
    {
      "number": "235",
      "title": "Vol 0 -  Chap 235",
      "url": "https://mangafire.to/read/dragon-ball-super.8235y/en/chapter-235"
    },
    {
      "number": "233",
      "title": "Vol 0 -  Chap 233",
      "url": "https://mangafire.to/read/dragon-ball-super.8235y/en/chapter-233"
    },
    {
      "number": "232",
      "title": "Vol 0 -  Chap 232",
      "url": "https://mangafire.to/read/dragon-ball-super.8235y/en/chapter-232"
    },
    {
      "number": "231",
      "title": "Vol 0 -  Chap 231",
      "url": "https://mangafire.to/read/dragon-ball-super.8235y/en/chapter-231"
    },
    {
      "number": "230",
      "title": "Vol 0 -  Chap 230",
      "url": "https://mangafire.to/read/dragon-ball-super.8235y/en/chapter-230"
    },
    {
      "number": "228",
      "title": "Vol 0 -  Chap 228",
      "url": "https://mangafire.to/read/dragon-ball-super.8235y/en/chapter-228"
    },
    {
      "number": "227",
      "title": "Vol 0 -  Chap 227",
      "url": "https://mangafire.to/read/dragon-ball-super.8235y/en/chapter-227"
    },
    {
      "number": "226",
      "title": "Vol 0 -  Chap 226",
      "url": "https://mangafire.to/read/dragon-ball-super.8235y/en/chapter-226"
    },
    {
      "number": "225",
      "title": "Vol 0 -  Chap 225",
      "url": "https://mangafire.to/read/dragon-ball-super.8235y/en/chapter-225"
    },
    {
      "number": "223",
      "title": "Vol 0 -  Chap 223",
      "url": "https://mangafire.to/read/dragon-ball-super.8235y/en/chapter-223"
    },
    {
      "number": "222",
      "title": "Vol 0 -  Chap 222",
      "url": "https://mangafire.to/read/dragon-ball-super.8235y/en/chapter-222"
    },
    {
      "number": "221",
      "title": "Vol 0 -  Chap 221",
      "url": "https://mangafire.to/read/dragon-ball-super.8235y/en/chapter-221"
    },
    {
      "number": "220",
      "title": "Vol 0 -  Chap 220",
      "url": "https://mangafire.to/read/dragon-ball-super.8235y/en/chapter-220"
    },
    {
      "number": "219",
      "title": "Vol 0 -  Chap 219",
      "url": "https://mangafire.to/read/dragon-ball-super.8235y/en/chapter-219"
    },
    {
      "number": "218",
      "title": "Vol 0 -  Chap 218",
      "url": "https://mangafire.to/read/dragon-ball-super.8235y/en/chapter-218"
    },
    {
      "number": "216",
      "title": "Vol 0 -  Chap 216",
      "url": "https://mangafire.to/read/dragon-ball-super.8235y/en/chapter-216"
    },
    {
      "number": "213",
      "title": "Vol 0 -  Chap 213",
      "url": "https://mangafire.to/read/dragon-ball-super.8235y/en/chapter-213"
    },
    {
      "number": "212",
      "title": "Vol 0 -  Chap 212",
      "url": "https://mangafire.to/read/dragon-ball-super.8235y/en/chapter-212"
    },
    {
      "number": "210",
      "title": "Vol 0 -  Chap 210",
      "url": "https://mangafire.to/read/dragon-ball-super.8235y/en/chapter-210"
    },
    {
      "number": "207",
      "title": "Vol 0 -  Chap 207",
      "url": "https://mangafire.to/read/dragon-ball-super.8235y/en/chapter-207"
    },
    {
      "number": "206",
      "title": "Vol 0 -  Chap 206",
      "url": "https://mangafire.to/read/dragon-ball-super.8235y/en/chapter-206"
    },
    {
      "number": "204",
      "title": "Vol 0 -  Chap 204",
      "url": "https://mangafire.to/read/dragon-ball-super.8235y/en/chapter-204"
    },
    {
      "number": "203",
      "title": "Vol 0 -  Chap 203",
      "url": "https://mangafire.to/read/dragon-ball-super.8235y/en/chapter-203"
    },
    {
      "number": "202",
      "title": "Vol 0 -  Chap 202",
      "url": "https://mangafire.to/read/dragon-ball-super.8235y/en/chapter-202"
    },
    {
      "number": "201",
      "title": "Vol 0 -  Chap 201",
      "url": "https://mangafire.to/read/dragon-ball-super.8235y/en/chapter-201"
    },
    {
      "number": "200",
      "title": "Vol 0 -  Chap 200",
      "url": "https://mangafire.to/read/dragon-ball-super.8235y/en/chapter-200"
    },
    {
      "number": "198",
      "title": "Vol 0 -  Chap 198",
      "url": "https://mangafire.to/read/dragon-ball-super.8235y/en/chapter-198"
    },
    {
      "number": "197",
      "title": "Vol 0 -  Chap 197",
      "url": "https://mangafire.to/read/dragon-ball-super.8235y/en/chapter-197"
    },
    {
      "number": "196",
      "title": "Vol 0 -  Chap 196",
      "url": "https://mangafire.to/read/dragon-ball-super.8235y/en/chapter-196"
    },
    {
      "number": "193",
      "title": "Vol 0 -  Chap 193",
      "url": "https://mangafire.to/read/dragon-ball-super.8235y/en/chapter-193"
    },
    {
      "number": "192",
      "title": "Vol 0 -  Chap 192",
      "url": "https://mangafire.to/read/dragon-ball-super.8235y/en/chapter-192"
    },
    {
      "number": "191",
      "title": "Vol 0 -  Chap 191",
      "url": "https://mangafire.to/read/dragon-ball-super.8235y/en/chapter-191"
    },
    {
      "number": "190",
      "title": "Vol 0 -  Chap 190",
      "url": "https://mangafire.to/read/dragon-ball-super.8235y/en/chapter-190"
    },
    {
      "number": "188",
      "title": "Vol 0 -  Chap 188",
      "url": "https://mangafire.to/read/dragon-ball-super.8235y/en/chapter-188"
    },
    {
      "number": "185",
      "title": "Vol 0 -  Chap 185",
      "url": "https://mangafire.to/read/dragon-ball-super.8235y/en/chapter-185"
    },
    {
      "number": "183",
      "title": "Vol 0 -  Chap 183",
      "url": "https://mangafire.to/read/dragon-ball-super.8235y/en/chapter-183"
    },
    {
      "number": "182",
      "title": "Vol 0 -  Chap 182",
      "url": "https://mangafire.to/read/dragon-ball-super.8235y/en/chapter-182"
    },
    {
      "number": "181",
      "title": "Vol 0 -  Chap 181",
      "url": "https://mangafire.to/read/dragon-ball-super.8235y/en/chapter-181"
    },
    {
      "number": "180",
      "title": "Vol 0 -  Chap 180",
      "url": "https://mangafire.to/read/dragon-ball-super.8235y/en/chapter-180"
    },
    {
      "number": "178",
      "title": "Vol 0 -  Chap 178",
      "url": "https://mangafire.to/read/dragon-ball-super.8235y/en/chapter-178"
    },
    {
      "number": "177",
      "title": "Vol 0 -  Chap 177",
      "url": "https://mangafire.to/read/dragon-ball-super.8235y/en/chapter-177"
    },
    {
      "number": "176",
      "title": "Vol 0 -  Chap 176",
      "url": "https://mangafire.to/read/dragon-ball-super.8235y/en/chapter-176"
    },
    {
      "number": "174",
      "title": "Vol 0 -  Chap 174",
      "url": "https://mangafire.to/read/dragon-ball-super.8235y/en/chapter-174"
    },
    {
      "number": "173",
      "title": "Vol 0 -  Chap 173",
      "url": "https://mangafire.to/read/dragon-ball-super.8235y/en/chapter-173"
    },
    {
      "number": "172",
      "title": "Vol 0 -  Chap 172",
      "url": "https://mangafire.to/read/dragon-ball-super.8235y/en/chapter-172"
    },
    {
      "number": "171",
      "title": "Vol 0 -  Chap 171",
      "url": "https://mangafire.to/read/dragon-ball-super.8235y/en/chapter-171"
    },
    {
      "number": "170",
      "title": "Vol 0 -  Chap 170",
      "url": "https://mangafire.to/read/dragon-ball-super.8235y/en/chapter-170"
    },
    {
      "number": "169",
      "title": "Vol 0 -  Chap 169",
      "url": "https://mangafire.to/read/dragon-ball-super.8235y/en/chapter-169"
    },
    {
      "number": "168",
      "title": "Vol 0 -  Chap 168",
      "url": "https://mangafire.to/read/dragon-ball-super.8235y/en/chapter-168"
    },
    {
      "number": "167",
      "title": "Vol 0 -  Chap 167",
      "url": "https://mangafire.to/read/dragon-ball-super.8235y/en/chapter-167"
    },
    {
      "number": "165",
      "title": "Vol 0 -  Chap 165",
      "url": "https://mangafire.to/read/dragon-ball-super.8235y/en/chapter-165"
    },
    {
      "number": "145",
      "title": "Vol 0 -  Chap 145",
      "url": "https://mangafire.to/read/dragon-ball-super.8235y/en/chapter-145"
    },
    {
      "number": "144",
      "title": "Vol 0 -  Chap 144",
      "url": "https://mangafire.to/read/dragon-ball-super.8235y/en/chapter-144"
    },
    {
      "number": "140",
      "title": "Vol 0 -  Chap 140",
      "url": "https://mangafire.to/read/dragon-ball-super.8235y/en/chapter-140"
    },
    {
      "number": "139",
      "title": "Vol 0 -  Chap 139",
      "url": "https://mangafire.to/read/dragon-ball-super.8235y/en/chapter-139"
    },
    {
      "number": "137",
      "title": "Vol 0 -  Chap 137",
      "url": "https://mangafire.to/read/dragon-ball-super.8235y/en/chapter-137"
    },
    {
      "number": "136",
      "title": "Vol 0 -  Chap 136",
      "url": "https://mangafire.to/read/dragon-ball-super.8235y/en/chapter-136"
    },
    {
      "number": "135",
      "title": "Vol 0 -  Chap 135",
      "url": "https://mangafire.to/read/dragon-ball-super.8235y/en/chapter-135"
    },
    {
      "number": "134",
      "title": "Vol 0 -  Chap 134",
      "url": "https://mangafire.to/read/dragon-ball-super.8235y/en/chapter-134"
    },
    {
      "number": "133",
      "title": "Vol 0 -  Chap 133",
      "url": "https://mangafire.to/read/dragon-ball-super.8235y/en/chapter-133"
    },
    {
      "number": "132",
      "title": "Vol 0 -  Chap 132",
      "url": "https://mangafire.to/read/dragon-ball-super.8235y/en/chapter-132"
    },
    {
      "number": "131",
      "title": "Vol 0 -  Chap 131",
      "url": "https://mangafire.to/read/dragon-ball-super.8235y/en/chapter-131"
    },
    {
      "number": "128",
      "title": "Vol 0 -  Chap 128",
      "url": "https://mangafire.to/read/dragon-ball-super.8235y/en/chapter-128"
    },
    {
      "number": "127",
      "title": "Vol 0 -  Chap 127",
      "url": "https://mangafire.to/read/dragon-ball-super.8235y/en/chapter-127"
    },
    {
      "number": "126",
      "title": "Vol 0 -  Chap 126",
      "url": "https://mangafire.to/read/dragon-ball-super.8235y/en/chapter-126"
    },
    {
      "number": "125",
      "title": "Vol 0 -  Chap 125",
      "url": "https://mangafire.to/read/dragon-ball-super.8235y/en/chapter-125"
    },
    {
      "number": "123",
      "title": "Vol 0 -  Chap 123",
      "url": "https://mangafire.to/read/dragon-ball-super.8235y/en/chapter-123"
    },
    {
      "number": "121",
      "title": "Vol 0 -  Chap 121",
      "url": "https://mangafire.to/read/dragon-ball-super.8235y/en/chapter-121"
    },
    {
      "number": "120",
      "title": "Vol 0 -  Chap 120",
      "url": "https://mangafire.to/read/dragon-ball-super.8235y/en/chapter-120"
    },
    {
      "number": "119",
      "title": "Vol 0 -  Chap 119",
      "url": "https://mangafire.to/read/dragon-ball-super.8235y/en/chapter-119"
    },
    {
      "number": "118",
      "title": "Vol 0 -  Chap 118",
      "url": "https://mangafire.to/read/dragon-ball-super.8235y/en/chapter-118"
    },
    {
      "number": "115",
      "title": "Vol 0 -  Chap 115",
      "url": "https://mangafire.to/read/dragon-ball-super.8235y/en/chapter-115"
    },
    {
      "number": "114",
      "title": "Vol 0 -  Chap 114",
      "url": "https://mangafire.to/read/dragon-ball-super.8235y/en/chapter-114"
    },
    {
      "number": "113",
      "title": "Vol 0 -  Chap 113",
      "url": "https://mangafire.to/read/dragon-ball-super.8235y/en/chapter-113"
    },
    {
      "number": "112",
      "title": "Vol 0 -  Chap 112",
      "url": "https://mangafire.to/read/dragon-ball-super.8235y/en/chapter-112"
    },
    {
      "number": "111",
      "title": "Vol 0 -  Chap 111",
      "url": "https://mangafire.to/read/dragon-ball-super.8235y/en/chapter-111"
    },
    {
      "number": "109",
      "title": "Vol 0 -  Chap 109",
      "url": "https://mangafire.to/read/dragon-ball-super.8235y/en/chapter-109"
    },
    {
      "number": "107",
      "title": "Vol 0 -  Chap 107",
      "url": "https://mangafire.to/read/dragon-ball-super.8235y/en/chapter-107"
    },
    {
      "number": "106",
      "title": "Vol 0 -  Chap 106",
      "url": "https://mangafire.to/read/dragon-ball-super.8235y/en/chapter-106"
    },
    {
      "number": "105",
      "title": "Vol 0 -  Chap 105",
      "url": "https://mangafire.to/read/dragon-ball-super.8235y/en/chapter-105"
    },
    {
      "number": "104",
      "title": "Vol 24 -  Chap 104",
      "url": "https://mangafire.to/read/dragon-ball-super.8235y/en/chapter-104"
    },
    {
      "number": "103",
      "title": "Vol 24 -  Chap 103",
      "url": "https://mangafire.to/read/dragon-ball-super.8235y/en/chapter-103"
    },
    {
      "number": "102",
      "title": "Vol 23 -  Chap 102",
      "url": "https://mangafire.to/read/dragon-ball-super.8235y/en/chapter-102"
    },
    {
      "number": "101",
      "title": "Vol 0 -  Chap 101",
      "url": "https://mangafire.to/read/dragon-ball-super.8235y/en/chapter-101"
    },
    {
      "number": "100",
      "title": "Vol 23 -  Chap 100",
      "url": "https://mangafire.to/read/dragon-ball-super.8235y/en/chapter-100"
    },
    {
      "number": "99",
      "title": "Vol 23 -  Chap 99",
      "url": "https://mangafire.to/read/dragon-ball-super.8235y/en/chapter-99"
    },
    {
      "number": "98",
      "title": "Vol 23 -  Chap 98",
      "url": "https://mangafire.to/read/dragon-ball-super.8235y/en/chapter-98"
    },
    {
      "number": "97",
      "title": "Vol 23 -  Chap 97",
      "url": "https://mangafire.to/read/dragon-ball-super.8235y/en/chapter-97"
    },
    {
      "number": "96",
      "title": "Vol 22 -  Chap 96",
      "url": "https://mangafire.to/read/dragon-ball-super.8235y/en/chapter-96"
    },
    {
      "number": "95",
      "title": "Vol 22 -  Chap 95",
      "url": "https://mangafire.to/read/dragon-ball-super.8235y/en/chapter-95"
    },
    {
      "number": "94",
      "title": "Vol 22 -  Chap 94",
      "url": "https://mangafire.to/read/dragon-ball-super.8235y/en/chapter-94"
    },
    {
      "number": "93",
      "title": "Vol 22 -  Chap 93",
      "url": "https://mangafire.to/read/dragon-ball-super.8235y/en/chapter-93"
    },
    {
      "number": "92",
      "title": "Vol 21 -  Chap 92",
      "url": "https://mangafire.to/read/dragon-ball-super.8235y/en/chapter-92"
    },
    {
      "number": "91",
      "title": "Vol 21 -  Chap 91",
      "url": "https://mangafire.to/read/dragon-ball-super.8235y/en/chapter-91"
    },
    {
      "number": "90",
      "title": "Vol 21 -  Chap 90",
      "url": "https://mangafire.to/read/dragon-ball-super.8235y/en/chapter-90"
    },
    {
      "number": "89",
      "title": "Vol 21 -  Chap 89",
      "url": "https://mangafire.to/read/dragon-ball-super.8235y/en/chapter-89"
    },
    {
      "number": "88",
      "title": "Vol 20 -  Chap 88",
      "url": "https://mangafire.to/read/dragon-ball-super.8235y/en/chapter-88"
    },
    {
      "number": "87",
      "title": "Vol 20 -  Chap 87",
      "url": "https://mangafire.to/read/dragon-ball-super.8235y/en/chapter-87"
    },
    {
      "number": "86",
      "title": "Vol 20 -  Chap 86",
      "url": "https://mangafire.to/read/dragon-ball-super.8235y/en/chapter-86"
    },
    {
      "number": "85",
      "title": "Vol 20 -  Chap 85",
      "url": "https://mangafire.to/read/dragon-ball-super.8235y/en/chapter-85"
    },
    {
      "number": "84",
      "title": "Vol 19 -  Chap 84",
      "url": "https://mangafire.to/read/dragon-ball-super.8235y/en/chapter-84"
    },
    {
      "number": "83",
      "title": "Vol 19 -  Chap 83",
      "url": "https://mangafire.to/read/dragon-ball-super.8235y/en/chapter-83"
    },
    {
      "number": "82",
      "title": "Vol 19 -  Chap 82",
      "url": "https://mangafire.to/read/dragon-ball-super.8235y/en/chapter-82"
    },
    {
      "number": "81",
      "title": "Vol 19 -  Chap 81",
      "url": "https://mangafire.to/read/dragon-ball-super.8235y/en/chapter-81"
    },
    {
      "number": "80",
      "title": "Vol 18 -  Chap 80",
      "url": "https://mangafire.to/read/dragon-ball-super.8235y/en/chapter-80"
    },
    {
      "number": "79",
      "title": "Vol 18 -  Chap 79",
      "url": "https://mangafire.to/read/dragon-ball-super.8235y/en/chapter-79"
    },
    {
      "number": "78",
      "title": "Vol 18 -  Chap 78",
      "url": "https://mangafire.to/read/dragon-ball-super.8235y/en/chapter-78"
    },
    {
      "number": "77",
      "title": "Vol 18 -  Chap 77",
      "url": "https://mangafire.to/read/dragon-ball-super.8235y/en/chapter-77"
    },
    {
      "number": "76",
      "title": "Vol 17 -  Chap 76",
      "url": "https://mangafire.to/read/dragon-ball-super.8235y/en/chapter-76"
    },
    {
      "number": "75",
      "title": "Vol 17 -  Chap 75",
      "url": "https://mangafire.to/read/dragon-ball-super.8235y/en/chapter-75"
    },
    {
      "number": "74",
      "title": "Vol 17 -  Chap 74",
      "url": "https://mangafire.to/read/dragon-ball-super.8235y/en/chapter-74"
    },
    {
      "number": "73",
      "title": "Vol 17 -  Chap 73",
      "url": "https://mangafire.to/read/dragon-ball-super.8235y/en/chapter-73"
    },
    {
      "number": "72",
      "title": "Vol 16 -  Chap 72",
      "url": "https://mangafire.to/read/dragon-ball-super.8235y/en/chapter-72"
    },
    {
      "number": "71",
      "title": "Vol 16 -  Chap 71",
      "url": "https://mangafire.to/read/dragon-ball-super.8235y/en/chapter-71"
    },
    {
      "number": "70",
      "title": "Vol 16 -  Chap 70",
      "url": "https://mangafire.to/read/dragon-ball-super.8235y/en/chapter-70"
    },
    {
      "number": "69",
      "title": "Vol 16 -  Chap 69",
      "url": "https://mangafire.to/read/dragon-ball-super.8235y/en/chapter-69"
    },
    {
      "number": "68",
      "title": "Vol 15 -  Chap 68",
      "url": "https://mangafire.to/read/dragon-ball-super.8235y/en/chapter-68"
    },
    {
      "number": "67",
      "title": "Vol 15 -  Chap 67",
      "url": "https://mangafire.to/read/dragon-ball-super.8235y/en/chapter-67"
    },
    {
      "number": "66",
      "title": "Vol 15 -  Chap 66",
      "url": "https://mangafire.to/read/dragon-ball-super.8235y/en/chapter-66"
    },
    {
      "number": "65",
      "title": "Vol 15 -  Chap 65",
      "url": "https://mangafire.to/read/dragon-ball-super.8235y/en/chapter-65"
    },
    {
      "number": "64",
      "title": "Vol 14 -  Chap 64",
      "url": "https://mangafire.to/read/dragon-ball-super.8235y/en/chapter-64"
    },
    {
      "number": "63",
      "title": "Vol 14 -  Chap 63",
      "url": "https://mangafire.to/read/dragon-ball-super.8235y/en/chapter-63"
    },
    {
      "number": "62",
      "title": "Vol 14 -  Chap 62",
      "url": "https://mangafire.to/read/dragon-ball-super.8235y/en/chapter-62"
    },
    {
      "number": "61",
      "title": "Vol 14 -  Chap 61",
      "url": "https://mangafire.to/read/dragon-ball-super.8235y/en/chapter-61"
    },
    {
      "number": "60",
      "title": "Vol 13 -  Chap 60",
      "url": "https://mangafire.to/read/dragon-ball-super.8235y/en/chapter-60"
    },
    {
      "number": "59",
      "title": "Vol 13 -  Chap 59",
      "url": "https://mangafire.to/read/dragon-ball-super.8235y/en/chapter-59"
    },
    {
      "number": "58",
      "title": "Vol 13 -  Chap 58",
      "url": "https://mangafire.to/read/dragon-ball-super.8235y/en/chapter-58"
    },
    {
      "number": "57",
      "title": "Vol 13 -  Chap 57",
      "url": "https://mangafire.to/read/dragon-ball-super.8235y/en/chapter-57"
    },
    {
      "number": "56",
      "title": "Vol 12 -  Chap 56",
      "url": "https://mangafire.to/read/dragon-ball-super.8235y/en/chapter-56"
    },
    {
      "number": "55",
      "title": "Vol 12 -  Chap 55",
      "url": "https://mangafire.to/read/dragon-ball-super.8235y/en/chapter-55"
    },
    {
      "number": "54",
      "title": "Vol 12 -  Chap 54",
      "url": "https://mangafire.to/read/dragon-ball-super.8235y/en/chapter-54"
    },
    {
      "number": "53",
      "title": "Vol 12 -  Chap 53",
      "url": "https://mangafire.to/read/dragon-ball-super.8235y/en/chapter-53"
    },
    {
      "number": "52",
      "title": "Vol 11 -  Chap 52",
      "url": "https://mangafire.to/read/dragon-ball-super.8235y/en/chapter-52"
    },
    {
      "number": "51",
      "title": "Vol 11 -  Chap 51",
      "url": "https://mangafire.to/read/dragon-ball-super.8235y/en/chapter-51"
    },
    {
      "number": "50",
      "title": "Vol 11 -  Chap 50",
      "url": "https://mangafire.to/read/dragon-ball-super.8235y/en/chapter-50"
    },
    {
      "number": "49",
      "title": "Vol 11 -  Chap 49",
      "url": "https://mangafire.to/read/dragon-ball-super.8235y/en/chapter-49"
    },
    {
      "number": "48.5",
      "title": "Vol 10 -  Chap 48.5",
      "url": "https://mangafire.to/read/dragon-ball-super.8235y/en/chapter-48.5"
    },
    {
      "number": "48",
      "title": "Vol 10 -  Chap 48",
      "url": "https://mangafire.to/read/dragon-ball-super.8235y/en/chapter-48"
    },
    {
      "number": "47",
      "title": "Vol 10 -  Chap 47",
      "url": "https://mangafire.to/read/dragon-ball-super.8235y/en/chapter-47"
    },
    {
      "number": "46",
      "title": "Vol 10 -  Chap 46",
      "url": "https://mangafire.to/read/dragon-ball-super.8235y/en/chapter-46"
    },
    {
      "number": "45",
      "title": "Vol 10 -  Chap 45",
      "url": "https://mangafire.to/read/dragon-ball-super.8235y/en/chapter-45"
    },
    {
      "number": "44",
      "title": "Vol 9 -  Chap 44",
      "url": "https://mangafire.to/read/dragon-ball-super.8235y/en/chapter-44"
    },
    {
      "number": "43",
      "title": "Vol 9 -  Chap 43",
      "url": "https://mangafire.to/read/dragon-ball-super.8235y/en/chapter-43"
    },
    {
      "number": "42",
      "title": "Vol 9 -  Chap 42",
      "url": "https://mangafire.to/read/dragon-ball-super.8235y/en/chapter-42"
    },
    {
      "number": "41",
      "title": "Vol 9 -  Chap 41",
      "url": "https://mangafire.to/read/dragon-ball-super.8235y/en/chapter-41"
    },
    {
      "number": "40",
      "title": "Vol 8 -  Chap 40",
      "url": "https://mangafire.to/read/dragon-ball-super.8235y/en/chapter-40"
    },
    {
      "number": "39",
      "title": "Vol 8 -  Chap 39",
      "url": "https://mangafire.to/read/dragon-ball-super.8235y/en/chapter-39"
    },
    {
      "number": "38",
      "title": "Vol 8 -  Chap 38",
      "url": "https://mangafire.to/read/dragon-ball-super.8235y/en/chapter-38"
    },
    {
      "number": "37",
      "title": "Vol 8 -  Chap 37",
      "url": "https://mangafire.to/read/dragon-ball-super.8235y/en/chapter-37"
    },
    {
      "number": "36",
      "title": "Vol 7 -  Chap 36",
      "url": "https://mangafire.to/read/dragon-ball-super.8235y/en/chapter-36"
    },
    {
      "number": "35",
      "title": "Vol 7 -  Chap 35",
      "url": "https://mangafire.to/read/dragon-ball-super.8235y/en/chapter-35"
    },
    {
      "number": "34",
      "title": "Vol 7 -  Chap 34",
      "url": "https://mangafire.to/read/dragon-ball-super.8235y/en/chapter-34"
    },
    {
      "number": "33",
      "title": "Vol 0 -  Chap 33",
      "url": "https://mangafire.to/read/dragon-ball-super.8235y/en/chapter-33"
    },
    {
      "number": "32",
      "title": "Vol 6 -  Chap 32",
      "url": "https://mangafire.to/read/dragon-ball-super.8235y/en/chapter-32"
    },
    {
      "number": "31",
      "title": "Vol 6 -  Chap 31",
      "url": "https://mangafire.to/read/dragon-ball-super.8235y/en/chapter-31"
    },
    {
      "number": "30.5",
      "title": "Vol 6 -  Chap 30.5",
      "url": "https://mangafire.to/read/dragon-ball-super.8235y/en/chapter-30.5"
    },
    {
      "number": "30",
      "title": "Vol 6 -  Chap 30",
      "url": "https://mangafire.to/read/dragon-ball-super.8235y/en/chapter-30"
    },
    {
      "number": "29",
      "title": "Vol 6 -  Chap 29",
      "url": "https://mangafire.to/read/dragon-ball-super.8235y/en/chapter-29"
    },
    {
      "number": "28",
      "title": "Vol 5 -  Chap 28",
      "url": "https://mangafire.to/read/dragon-ball-super.8235y/en/chapter-28"
    },
    {
      "number": "27",
      "title": "Vol 5 -  Chap 27",
      "url": "https://mangafire.to/read/dragon-ball-super.8235y/en/chapter-27"
    },
    {
      "number": "26",
      "title": "Vol 5 -  Chap 26",
      "url": "https://mangafire.to/read/dragon-ball-super.8235y/en/chapter-26"
    },
    {
      "number": "25",
      "title": "Vol 5 -  Chap 25",
      "url": "https://mangafire.to/read/dragon-ball-super.8235y/en/chapter-25"
    },
    {
      "number": "24",
      "title": "Vol 4 -  Chap 24",
      "url": "https://mangafire.to/read/dragon-ball-super.8235y/en/chapter-24"
    },
    {
      "number": "23",
      "title": "Vol 4 -  Chap 23",
      "url": "https://mangafire.to/read/dragon-ball-super.8235y/en/chapter-23"
    },
    {
      "number": "22",
      "title": "Vol 4 -  Chap 22",
      "url": "https://mangafire.to/read/dragon-ball-super.8235y/en/chapter-22"
    },
    {
      "number": "21",
      "title": "Vol 4 -  Chap 21",
      "url": "https://mangafire.to/read/dragon-ball-super.8235y/en/chapter-21"
    },
    {
      "number": "20",
      "title": "Vol 3 -  Chap 20",
      "url": "https://mangafire.to/read/dragon-ball-super.8235y/en/chapter-20"
    },
    {
      "number": "19",
      "title": "Vol 3 -  Chap 19",
      "url": "https://mangafire.to/read/dragon-ball-super.8235y/en/chapter-19"
    },
    {
      "number": "18",
      "title": "Vol 3 -  Chap 18",
      "url": "https://mangafire.to/read/dragon-ball-super.8235y/en/chapter-18"
    },
    {
      "number": "17",
      "title": "Vol 3 -  Chap 17",
      "url": "https://mangafire.to/read/dragon-ball-super.8235y/en/chapter-17"
    },
    {
      "number": "16",
      "title": "Vol 3 -  Chap 16",
      "url": "https://mangafire.to/read/dragon-ball-super.8235y/en/chapter-16"
    },
    {
      "number": "15",
      "title": "Vol 2 -  Chap 15",
      "url": "https://mangafire.to/read/dragon-ball-super.8235y/en/chapter-15"
    },
    {
      "number": "14",
      "title": "Vol 2 -  Chap 14",
      "url": "https://mangafire.to/read/dragon-ball-super.8235y/en/chapter-14"
    },
    {
      "number": "13",
      "title": "Vol 2 -  Chap 13",
      "url": "https://mangafire.to/read/dragon-ball-super.8235y/en/chapter-13"
    },
    {
      "number": "12",
      "title": "Vol 2 -  Chap 12",
      "url": "https://mangafire.to/read/dragon-ball-super.8235y/en/chapter-12"
    },
    {
      "number": "11",
      "title": "Vol 2 -  Chap 11",
      "url": "https://mangafire.to/read/dragon-ball-super.8235y/en/chapter-11"
    },
    {
      "number": "10",
      "title": "Vol 2 -  Chap 10",
      "url": "https://mangafire.to/read/dragon-ball-super.8235y/en/chapter-10"
    },
    {
      "number": "9",
      "title": "Vol 1 -  Chap 9",
      "url": "https://mangafire.to/read/dragon-ball-super.8235y/en/chapter-9"
    },
    {
      "number": "8",
      "title": "Vol 1 -  Chap 8",
      "url": "https://mangafire.to/read/dragon-ball-super.8235y/en/chapter-8"
    },
    {
      "number": "7",
      "title": "Vol 1 -  Chap 7",
      "url": "https://mangafire.to/read/dragon-ball-super.8235y/en/chapter-7"
    },
    {
      "number": "6",
      "title": "Vol 1 -  Chap 6",
      "url": "https://mangafire.to/read/dragon-ball-super.8235y/en/chapter-6"
    },
    {
      "number": "5",
      "title": "Vol 1 -  Chap 5",
      "url": "https://mangafire.to/read/dragon-ball-super.8235y/en/chapter-5"
    },
    {
      "number": "4",
      "title": "Vol 1 -  Chap 4",
      "url": "https://mangafire.to/read/dragon-ball-super.8235y/en/chapter-4"
    },
    {
      "number": "3",
      "title": "Vol 1 -  Chap 3",
      "url": "https://mangafire.to/read/dragon-ball-super.8235y/en/chapter-3"
    },
    {
      "number": "2",
      "title": "Vol 1 -  Chap 2",
      "url": "https://mangafire.to/read/dragon-ball-super.8235y/en/chapter-2"
    },
    {
      "number": "1",
      "title": "Vol 1 -  Chap 1",
      "url": "https://mangafire.to/read/dragon-ball-super.8235y/en/chapter-1"
    }
  ],
  "fetched_at": "2026-04-26T23:00:59Z"
}