{
  "slug": "era-kokyuu-no-imouto-o-kokoro-no-sasae-ni-shite-iru-ane-no-ohanashii.mqv3v",
  "title": "Era Kokyuu no Imouto o Kokoro no Sasae ni Shite iru Ane no Ohanashi",
  "cover": "https://static.mfcdn.nl/3aa9/i/9/95/da60f7045a1a04bbde01520eb24c793e@100.jpg",
  "description": "Era Kokyuu no Imouto o Kokoro no Sasae ni Shite iru Ane no Ohanashi manga, read all chapters here, the latest chapter 0 is available. Read Era Kokyuu no Imouto o Kokoro no Sasae ni Shite iru Ane no Ohanashi raw, multiple language. READ NOW!!",
  "status": "Completed",
  "genres": [
    "Action",
    "Adventure",
    "Avant Garde",
    "Boys Love",
    "Comedy",
    "Demons",
    "Drama",
    "Ecchi",
    "Fantasy",
    "Girls Love",
    "Gourmet",
    "Harem",
    "Horror",
    "Isekai",
    "Iyashikei",
    "Josei",
    "Kids",
    "Magic",
    "Mahou Shoujo",
    "Martial Arts",
    "Mecha",
    "Military",
    "Music",
    "Mystery",
    "Parody",
    "Psychological",
    "Reverse Harem",
    "Romance",
    "School",
    "Sci-Fi",
    "Seinen",
    "Shoujo",
    "Shounen",
    "Slice of Life",
    "Space",
    "Sports",
    "Super Power",
    "Supernatural",
    "Suspense",
    "Thriller",
    "Vampire",
    "Psychological"
  ],
  "chapters": [
    {
      "number": "0",
      "title": "Chap 0",
      "url": "https://mangafire.to/read/era-kokyuu-no-imouto-o-kokoro-no-sasae-ni-shite-iru-ane-no-ohanashii.mqv3v/en/chapter-0"
    }
  ],
  "fetched_at": "2026-05-03T08:08:56Z"
}