{
  "slug": "gagjaui-sigsaa.8n4oy",
  "title": "Gagjaui Sigsa",
  "cover": "https://static.mfcdn.nl/f149/i/f/f4/f4b48fcd9c58423b40ade03b3dae5bc4@100.jpg",
  "description": "Gagjaui Sigsa manga, read all chapters here, the latest chapter 4 is available. Read Gagjaui Sigsa raw, multiple language. READ NOW!!",
  "status": "Releasing",
  "genres": [
    "Action",
    "Adventure",
    "Avant Garde",
    "Boys Love",
    "Comedy",
    "Demons",
    "Drama",
    "Ecchi",
    "Fantasy",
    "Girls Love",
    "Gourmet",
    "Harem",
    "Horror",
    "Isekai",
    "Iyashikei",
    "Josei",
    "Kids",
    "Magic",
    "Mahou Shoujo",
    "Martial Arts",
    "Mecha",
    "Military",
    "Music",
    "Mystery",
    "Parody",
    "Psychological",
    "Reverse Harem",
    "Romance",
    "School",
    "Sci-Fi",
    "Seinen",
    "Shoujo",
    "Shounen",
    "Slice of Life",
    "Space",
    "Sports",
    "Super Power",
    "Supernatural",
    "Suspense",
    "Thriller",
    "Vampire",
    "Romance",
    "Supernatural",
    "Horror",
    "Psychological"
  ],
  "chapters": [
    {
      "number": "4",
      "title": "Chap 4",
      "url": "https://mangafire.to/read/gagjaui-sigsaa.8n4oy/en/chapter-4"
    },
    {
      "number": "3",
      "title": "Chap 3",
      "url": "https://mangafire.to/read/gagjaui-sigsaa.8n4oy/en/chapter-3"
    },
    {
      "number": "2",
      "title": "Chap 2",
      "url": "https://mangafire.to/read/gagjaui-sigsaa.8n4oy/en/chapter-2"
    },
    {
      "number": "1.1",
      "title": "Chap 1.1",
      "url": "https://mangafire.to/read/gagjaui-sigsaa.8n4oy/en/chapter-1.1"
    },
    {
      "number": "1",
      "title": "Chap 1",
      "url": "https://mangafire.to/read/gagjaui-sigsaa.8n4oy/en/chapter-1"
    },
    {
      "number": "0",
      "title": "Chap 0",
      "url": "https://mangafire.to/read/gagjaui-sigsaa.8n4oy/en/chapter-0"
    }
  ],
  "fetched_at": "2026-04-26T23:38:45Z"
}