{
  "slug": "gg.l2rq",
  "title": "G",
  "cover": "https://static.mfcdn.nl/c904/i/b/b9/b96db0e0eea97dcf5652264ebeed93a7@100.jpg",
  "description": "G manga, read all chapters here, the latest chapter 0 is available. Read G raw, multiple language. READ NOW!!",
  "status": "Completed",
  "genres": [
    "Action",
    "Adventure",
    "Avant Garde",
    "Boys Love",
    "Comedy",
    "Demons",
    "Drama",
    "Ecchi",
    "Fantasy",
    "Girls Love",
    "Gourmet",
    "Harem",
    "Horror",
    "Isekai",
    "Iyashikei",
    "Josei",
    "Kids",
    "Magic",
    "Mahou Shoujo",
    "Martial Arts",
    "Mecha",
    "Military",
    "Music",
    "Mystery",
    "Parody",
    "Psychological",
    "Reverse Harem",
    "Romance",
    "School",
    "Sci-Fi",
    "Seinen",
    "Shoujo",
    "Shounen",
    "Slice of Life",
    "Space",
    "Sports",
    "Super Power",
    "Supernatural",
    "Suspense",
    "Thriller",
    "Vampire",
    "Mystery",
    "Sci-Fi",
    "Supernatural",
    "Adventure",
    "Psychological",
    "Seinen"
  ],
  "chapters": [
    {
      "number": "0",
      "title": "Chap 0",
      "url": "https://mangafire.to/read/gg.l2rq/en/chapter-0"
    }
  ],
  "fetched_at": "2026-04-27T08:27:45Z"
}