{
  "slug": "her-special-seatt.o2v5",
  "title": "Her Special Seat",
  "cover": "https://static.mfcdn.nl/73a4/i/1/11/113534a5fe4702f5a427c168351a412e@100.jpg",
  "description": "Her Special Seat manga, read all chapters here, the latest chapter 0 is available. Read Her Special Seat raw, multiple language. READ NOW!!",
  "status": "Completed",
  "genres": [
    "Action",
    "Adventure",
    "Avant Garde",
    "Boys Love",
    "Comedy",
    "Demons",
    "Drama",
    "Ecchi",
    "Fantasy",
    "Girls Love",
    "Gourmet",
    "Harem",
    "Horror",
    "Isekai",
    "Iyashikei",
    "Josei",
    "Kids",
    "Magic",
    "Mahou Shoujo",
    "Martial Arts",
    "Mecha",
    "Military",
    "Music",
    "Mystery",
    "Parody",
    "Psychological",
    "Reverse Harem",
    "Romance",
    "School",
    "Sci-Fi",
    "Seinen",
    "Shoujo",
    "Shounen",
    "Slice of Life",
    "Space",
    "Sports",
    "Super Power",
    "Supernatural",
    "Suspense",
    "Thriller",
    "Vampire",
    "Supernatural",
    "Seinen",
    "Slice of Life"
  ],
  "chapters": [
    {
      "number": "0",
      "title": "Chap 0",
      "url": "https://mangafire.to/read/her-special-seatt.o2v5/en/chapter-0"
    }
  ],
  "fetched_at": "2026-04-27T01:14:16Z"
}