{
  "slug": "holiday-yasumis-twitter-shortss.ppkq9",
  "title": "Holiday Yasumi's Twitter Shorts",
  "cover": "https://static.mfcdn.nl/1f9f/i/e/e2/e2003b7959c9fbea20ba65519d6e41de@100.jpg",
  "description": "Holiday Yasumi's Twitter Shorts manga, read all chapters here, the latest chapter 820 is available. Read Holiday Yasumi's Twitter Shorts raw, multiple language. READ NOW!!",
  "status": "Releasing",
  "genres": [
    "Action",
    "Adventure",
    "Avant Garde",
    "Boys Love",
    "Comedy",
    "Demons",
    "Drama",
    "Ecchi",
    "Fantasy",
    "Girls Love",
    "Gourmet",
    "Harem",
    "Horror",
    "Isekai",
    "Iyashikei",
    "Josei",
    "Kids",
    "Magic",
    "Mahou Shoujo",
    "Martial Arts",
    "Mecha",
    "Military",
    "Music",
    "Mystery",
    "Parody",
    "Psychological",
    "Reverse Harem",
    "Romance",
    "School",
    "Sci-Fi",
    "Seinen",
    "Shoujo",
    "Shounen",
    "Slice of Life",
    "Space",
    "Sports",
    "Super Power",
    "Supernatural",
    "Suspense",
    "Thriller",
    "Vampire",
    "Comedy"
  ],
  "chapters": [
    {
      "number": "820",
      "title": "Chap 820",
      "url": "https://mangafire.to/read/holiday-yasumis-twitter-shortss.ppkq9/en/chapter-820"
    },
    {
      "number": "819",
      "title": "Chap 819",
      "url": "https://mangafire.to/read/holiday-yasumis-twitter-shortss.ppkq9/en/chapter-819"
    },
    {
      "number": "814",
      "title": "Chap 814",
      "url": "https://mangafire.to/read/holiday-yasumis-twitter-shortss.ppkq9/en/chapter-814"
    },
    {
      "number": "813",
      "title": "Chap 813",
      "url": "https://mangafire.to/read/holiday-yasumis-twitter-shortss.ppkq9/en/chapter-813"
    },
    {
      "number": "803",
      "title": "Chap 803",
      "url": "https://mangafire.to/read/holiday-yasumis-twitter-shortss.ppkq9/en/chapter-803"
    },
    {
      "number": "802",
      "title": "Chap 802",
      "url": "https://mangafire.to/read/holiday-yasumis-twitter-shortss.ppkq9/en/chapter-802"
    },
    {
      "number": "801",
      "title": "Chap 801",
      "url": "https://mangafire.to/read/holiday-yasumis-twitter-shortss.ppkq9/en/chapter-801"
    },
    {
      "number": "800",
      "title": "Chap 800",
      "url": "https://mangafire.to/read/holiday-yasumis-twitter-shortss.ppkq9/en/chapter-800"
    },
    {
      "number": "799",
      "title": "Chap 799",
      "url": "https://mangafire.to/read/holiday-yasumis-twitter-shortss.ppkq9/en/chapter-799"
    },
    {
      "number": "788",
      "title": "Chap 788",
      "url": "https://mangafire.to/read/holiday-yasumis-twitter-shortss.ppkq9/en/chapter-788"
    },
    {
      "number": "784",
      "title": "Chap 784",
      "url": "https://mangafire.to/read/holiday-yasumis-twitter-shortss.ppkq9/en/chapter-784"
    },
    {
      "number": "782",
      "title": "Chap 782",
      "url": "https://mangafire.to/read/holiday-yasumis-twitter-shortss.ppkq9/en/chapter-782"
    },
    {
      "number": "778",
      "title": "Chap 778",
      "url": "https://mangafire.to/read/holiday-yasumis-twitter-shortss.ppkq9/en/chapter-778"
    },
    {
      "number": "773",
      "title": "Chap 773",
      "url": "https://mangafire.to/read/holiday-yasumis-twitter-shortss.ppkq9/en/chapter-773"
    },
    {
      "number": "764",
      "title": "Chap 764",
      "url": "https://mangafire.to/read/holiday-yasumis-twitter-shortss.ppkq9/en/chapter-764"
    },
    {
      "number": "763",
      "title": "Chap 763",
      "url": "https://mangafire.to/read/holiday-yasumis-twitter-shortss.ppkq9/en/chapter-763"
    },
    {
      "number": "760",
      "title": "Chap 760",
      "url": "https://mangafire.to/read/holiday-yasumis-twitter-shortss.ppkq9/en/chapter-760"
    },
    {
      "number": "755",
      "title": "Chap 755",
      "url": "https://mangafire.to/read/holiday-yasumis-twitter-shortss.ppkq9/en/chapter-755"
    },
    {
      "number": "754",
      "title": "Chap 754",
      "url": "https://mangafire.to/read/holiday-yasumis-twitter-shortss.ppkq9/en/chapter-754"
    },
    {
      "number": "753",
      "title": "Chap 753",
      "url": "https://mangafire.to/read/holiday-yasumis-twitter-shortss.ppkq9/en/chapter-753"
    },
    {
      "number": "748",
      "title": "Chap 748",
      "url": "https://mangafire.to/read/holiday-yasumis-twitter-shortss.ppkq9/en/chapter-748"
    },
    {
      "number": "747",
      "title": "Chap 747",
      "url": "https://mangafire.to/read/holiday-yasumis-twitter-shortss.ppkq9/en/chapter-747"
    },
    {
      "number": "745",
      "title": "Chap 745",
      "url": "https://mangafire.to/read/holiday-yasumis-twitter-shortss.ppkq9/en/chapter-745"
    },
    {
      "number": "742",
      "title": "Chap 742",
      "url": "https://mangafire.to/read/holiday-yasumis-twitter-shortss.ppkq9/en/chapter-742"
    },
    {
      "number": "740",
      "title": "Chap 740",
      "url": "https://mangafire.to/read/holiday-yasumis-twitter-shortss.ppkq9/en/chapter-740"
    },
    {
      "number": "739",
      "title": "Chap 739",
      "url": "https://mangafire.to/read/holiday-yasumis-twitter-shortss.ppkq9/en/chapter-739"
    },
    {
      "number": "735",
      "title": "Chap 735",
      "url": "https://mangafire.to/read/holiday-yasumis-twitter-shortss.ppkq9/en/chapter-735"
    },
    {
      "number": "733",
      "title": "Chap 733",
      "url": "https://mangafire.to/read/holiday-yasumis-twitter-shortss.ppkq9/en/chapter-733"
    },
    {
      "number": "732",
      "title": "Chap 732",
      "url": "https://mangafire.to/read/holiday-yasumis-twitter-shortss.ppkq9/en/chapter-732"
    },
    {
      "number": "726",
      "title": "Chap 726",
      "url": "https://mangafire.to/read/holiday-yasumis-twitter-shortss.ppkq9/en/chapter-726"
    },
    {
      "number": "722",
      "title": "Chap 722",
      "url": "https://mangafire.to/read/holiday-yasumis-twitter-shortss.ppkq9/en/chapter-722"
    },
    {
      "number": "721",
      "title": "Chap 721",
      "url": "https://mangafire.to/read/holiday-yasumis-twitter-shortss.ppkq9/en/chapter-721"
    },
    {
      "number": "719",
      "title": "Chap 719",
      "url": "https://mangafire.to/read/holiday-yasumis-twitter-shortss.ppkq9/en/chapter-719"
    },
    {
      "number": "717",
      "title": "Chap 717",
      "url": "https://mangafire.to/read/holiday-yasumis-twitter-shortss.ppkq9/en/chapter-717"
    },
    {
      "number": "715",
      "title": "Chap 715",
      "url": "https://mangafire.to/read/holiday-yasumis-twitter-shortss.ppkq9/en/chapter-715"
    },
    {
      "number": "712",
      "title": "Chap 712",
      "url": "https://mangafire.to/read/holiday-yasumis-twitter-shortss.ppkq9/en/chapter-712"
    },
    {
      "number": "707",
      "title": "Chap 707",
      "url": "https://mangafire.to/read/holiday-yasumis-twitter-shortss.ppkq9/en/chapter-707"
    },
    {
      "number": "704",
      "title": "Chap 704",
      "url": "https://mangafire.to/read/holiday-yasumis-twitter-shortss.ppkq9/en/chapter-704"
    },
    {
      "number": "698",
      "title": "Chap 698",
      "url": "https://mangafire.to/read/holiday-yasumis-twitter-shortss.ppkq9/en/chapter-698"
    },
    {
      "number": "696",
      "title": "Chap 696",
      "url": "https://mangafire.to/read/holiday-yasumis-twitter-shortss.ppkq9/en/chapter-696"
    },
    {
      "number": "683",
      "title": "Chap 683",
      "url": "https://mangafire.to/read/holiday-yasumis-twitter-shortss.ppkq9/en/chapter-683"
    },
    {
      "number": "681",
      "title": "Chap 681",
      "url": "https://mangafire.to/read/holiday-yasumis-twitter-shortss.ppkq9/en/chapter-681"
    },
    {
      "number": "677",
      "title": "Chap 677",
      "url": "https://mangafire.to/read/holiday-yasumis-twitter-shortss.ppkq9/en/chapter-677"
    },
    {
      "number": "674",
      "title": "Chap 674",
      "url": "https://mangafire.to/read/holiday-yasumis-twitter-shortss.ppkq9/en/chapter-674"
    },
    {
      "number": "670",
      "title": "Chap 670",
      "url": "https://mangafire.to/read/holiday-yasumis-twitter-shortss.ppkq9/en/chapter-670"
    },
    {
      "number": "668",
      "title": "Chap 668",
      "url": "https://mangafire.to/read/holiday-yasumis-twitter-shortss.ppkq9/en/chapter-668"
    },
    {
      "number": "661",
      "title": "Chap 661",
      "url": "https://mangafire.to/read/holiday-yasumis-twitter-shortss.ppkq9/en/chapter-661"
    },
    {
      "number": "660",
      "title": "Chap 660",
      "url": "https://mangafire.to/read/holiday-yasumis-twitter-shortss.ppkq9/en/chapter-660"
    },
    {
      "number": "659",
      "title": "Chap 659",
      "url": "https://mangafire.to/read/holiday-yasumis-twitter-shortss.ppkq9/en/chapter-659"
    },
    {
      "number": "658",
      "title": "Chap 658",
      "url": "https://mangafire.to/read/holiday-yasumis-twitter-shortss.ppkq9/en/chapter-658"
    },
    {
      "number": "655",
      "title": "Chap 655",
      "url": "https://mangafire.to/read/holiday-yasumis-twitter-shortss.ppkq9/en/chapter-655"
    },
    {
      "number": "652",
      "title": "Chap 652",
      "url": "https://mangafire.to/read/holiday-yasumis-twitter-shortss.ppkq9/en/chapter-652"
    },
    {
      "number": "646",
      "title": "Chap 646",
      "url": "https://mangafire.to/read/holiday-yasumis-twitter-shortss.ppkq9/en/chapter-646"
    },
    {
      "number": "643",
      "title": "Chap 643",
      "url": "https://mangafire.to/read/holiday-yasumis-twitter-shortss.ppkq9/en/chapter-643"
    },
    {
      "number": "636",
      "title": "Chap 636",
      "url": "https://mangafire.to/read/holiday-yasumis-twitter-shortss.ppkq9/en/chapter-636"
    },
    {
      "number": "627",
      "title": "Chap 627",
      "url": "https://mangafire.to/read/holiday-yasumis-twitter-shortss.ppkq9/en/chapter-627"
    },
    {
      "number": "609",
      "title": "Chap 609",
      "url": "https://mangafire.to/read/holiday-yasumis-twitter-shortss.ppkq9/en/chapter-609"
    },
    {
      "number": "603",
      "title": "Chap 603",
      "url": "https://mangafire.to/read/holiday-yasumis-twitter-shortss.ppkq9/en/chapter-603"
    },
    {
      "number": "595",
      "title": "Chap 595",
      "url": "https://mangafire.to/read/holiday-yasumis-twitter-shortss.ppkq9/en/chapter-595"
    },
    {
      "number": "591",
      "title": "Chap 591",
      "url": "https://mangafire.to/read/holiday-yasumis-twitter-shortss.ppkq9/en/chapter-591"
    },
    {
      "number": "575",
      "title": "Chap 575",
      "url": "https://mangafire.to/read/holiday-yasumis-twitter-shortss.ppkq9/en/chapter-575"
    },
    {
      "number": "571",
      "title": "Chap 571",
      "url": "https://mangafire.to/read/holiday-yasumis-twitter-shortss.ppkq9/en/chapter-571"
    },
    {
      "number": "563",
      "title": "Chap 563",
      "url": "https://mangafire.to/read/holiday-yasumis-twitter-shortss.ppkq9/en/chapter-563"
    },
    {
      "number": "527",
      "title": "Chap 527",
      "url": "https://mangafire.to/read/holiday-yasumis-twitter-shortss.ppkq9/en/chapter-527"
    },
    {
      "number": "526",
      "title": "Chap 526",
      "url": "https://mangafire.to/read/holiday-yasumis-twitter-shortss.ppkq9/en/chapter-526"
    },
    {
      "number": "525",
      "title": "Chap 525",
      "url": "https://mangafire.to/read/holiday-yasumis-twitter-shortss.ppkq9/en/chapter-525"
    },
    {
      "number": "522",
      "title": "Chap 522",
      "url": "https://mangafire.to/read/holiday-yasumis-twitter-shortss.ppkq9/en/chapter-522"
    },
    {
      "number": "504",
      "title": "Chap 504",
      "url": "https://mangafire.to/read/holiday-yasumis-twitter-shortss.ppkq9/en/chapter-504"
    },
    {
      "number": "490",
      "title": "Chap 490",
      "url": "https://mangafire.to/read/holiday-yasumis-twitter-shortss.ppkq9/en/chapter-490"
    },
    {
      "number": "489",
      "title": "Chap 489",
      "url": "https://mangafire.to/read/holiday-yasumis-twitter-shortss.ppkq9/en/chapter-489"
    },
    {
      "number": "488",
      "title": "Chap 488",
      "url": "https://mangafire.to/read/holiday-yasumis-twitter-shortss.ppkq9/en/chapter-488"
    },
    {
      "number": "476",
      "title": "Chap 476",
      "url": "https://mangafire.to/read/holiday-yasumis-twitter-shortss.ppkq9/en/chapter-476"
    },
    {
      "number": "471",
      "title": "Chap 471",
      "url": "https://mangafire.to/read/holiday-yasumis-twitter-shortss.ppkq9/en/chapter-471"
    },
    {
      "number": "469",
      "title": "Chap 469",
      "url": "https://mangafire.to/read/holiday-yasumis-twitter-shortss.ppkq9/en/chapter-469"
    },
    {
      "number": "457",
      "title": "Chap 457",
      "url": "https://mangafire.to/read/holiday-yasumis-twitter-shortss.ppkq9/en/chapter-457"
    },
    {
      "number": "450",
      "title": "Chap 450",
      "url": "https://mangafire.to/read/holiday-yasumis-twitter-shortss.ppkq9/en/chapter-450"
    },
    {
      "number": "447",
      "title": "Chap 447",
      "url": "https://mangafire.to/read/holiday-yasumis-twitter-shortss.ppkq9/en/chapter-447"
    },
    {
      "number": "444",
      "title": "Chap 444",
      "url": "https://mangafire.to/read/holiday-yasumis-twitter-shortss.ppkq9/en/chapter-444"
    },
    {
      "number": "443",
      "title": "Chap 443",
      "url": "https://mangafire.to/read/holiday-yasumis-twitter-shortss.ppkq9/en/chapter-443"
    },
    {
      "number": "437",
      "title": "Chap 437",
      "url": "https://mangafire.to/read/holiday-yasumis-twitter-shortss.ppkq9/en/chapter-437"
    },
    {
      "number": "434",
      "title": "Chap 434",
      "url": "https://mangafire.to/read/holiday-yasumis-twitter-shortss.ppkq9/en/chapter-434"
    },
    {
      "number": "425",
      "title": "Chap 425",
      "url": "https://mangafire.to/read/holiday-yasumis-twitter-shortss.ppkq9/en/chapter-425"
    },
    {
      "number": "424",
      "title": "Chap 424",
      "url": "https://mangafire.to/read/holiday-yasumis-twitter-shortss.ppkq9/en/chapter-424"
    },
    {
      "number": "422",
      "title": "Chap 422",
      "url": "https://mangafire.to/read/holiday-yasumis-twitter-shortss.ppkq9/en/chapter-422"
    },
    {
      "number": "421",
      "title": "Chap 421",
      "url": "https://mangafire.to/read/holiday-yasumis-twitter-shortss.ppkq9/en/chapter-421"
    },
    {
      "number": "417",
      "title": "Chap 417",
      "url": "https://mangafire.to/read/holiday-yasumis-twitter-shortss.ppkq9/en/chapter-417"
    },
    {
      "number": "416",
      "title": "Chap 416",
      "url": "https://mangafire.to/read/holiday-yasumis-twitter-shortss.ppkq9/en/chapter-416"
    },
    {
      "number": "414",
      "title": "Chap 414",
      "url": "https://mangafire.to/read/holiday-yasumis-twitter-shortss.ppkq9/en/chapter-414"
    },
    {
      "number": "408",
      "title": "Chap 408",
      "url": "https://mangafire.to/read/holiday-yasumis-twitter-shortss.ppkq9/en/chapter-408"
    },
    {
      "number": "401",
      "title": "Chap 401",
      "url": "https://mangafire.to/read/holiday-yasumis-twitter-shortss.ppkq9/en/chapter-401"
    },
    {
      "number": "397",
      "title": "Chap 397",
      "url": "https://mangafire.to/read/holiday-yasumis-twitter-shortss.ppkq9/en/chapter-397"
    },
    {
      "number": "392",
      "title": "Chap 392",
      "url": "https://mangafire.to/read/holiday-yasumis-twitter-shortss.ppkq9/en/chapter-392"
    },
    {
      "number": "387",
      "title": "Chap 387",
      "url": "https://mangafire.to/read/holiday-yasumis-twitter-shortss.ppkq9/en/chapter-387"
    },
    {
      "number": "379",
      "title": "Chap 379",
      "url": "https://mangafire.to/read/holiday-yasumis-twitter-shortss.ppkq9/en/chapter-379"
    },
    {
      "number": "378",
      "title": "Chap 378",
      "url": "https://mangafire.to/read/holiday-yasumis-twitter-shortss.ppkq9/en/chapter-378"
    },
    {
      "number": "374",
      "title": "Chap 374",
      "url": "https://mangafire.to/read/holiday-yasumis-twitter-shortss.ppkq9/en/chapter-374"
    },
    {
      "number": "370",
      "title": "Chap 370",
      "url": "https://mangafire.to/read/holiday-yasumis-twitter-shortss.ppkq9/en/chapter-370"
    },
    {
      "number": "361",
      "title": "Chap 361",
      "url": "https://mangafire.to/read/holiday-yasumis-twitter-shortss.ppkq9/en/chapter-361"
    },
    {
      "number": "360",
      "title": "Chap 360",
      "url": "https://mangafire.to/read/holiday-yasumis-twitter-shortss.ppkq9/en/chapter-360"
    },
    {
      "number": "358",
      "title": "Chap 358",
      "url": "https://mangafire.to/read/holiday-yasumis-twitter-shortss.ppkq9/en/chapter-358"
    },
    {
      "number": "350",
      "title": "Chap 350",
      "url": "https://mangafire.to/read/holiday-yasumis-twitter-shortss.ppkq9/en/chapter-350"
    },
    {
      "number": "348",
      "title": "Chap 348",
      "url": "https://mangafire.to/read/holiday-yasumis-twitter-shortss.ppkq9/en/chapter-348"
    },
    {
      "number": "346",
      "title": "Chap 346",
      "url": "https://mangafire.to/read/holiday-yasumis-twitter-shortss.ppkq9/en/chapter-346"
    },
    {
      "number": "332",
      "title": "Chap 332",
      "url": "https://mangafire.to/read/holiday-yasumis-twitter-shortss.ppkq9/en/chapter-332"
    },
    {
      "number": "329",
      "title": "Chap 329",
      "url": "https://mangafire.to/read/holiday-yasumis-twitter-shortss.ppkq9/en/chapter-329"
    },
    {
      "number": "324",
      "title": "Chap 324",
      "url": "https://mangafire.to/read/holiday-yasumis-twitter-shortss.ppkq9/en/chapter-324"
    },
    {
      "number": "323",
      "title": "Chap 323",
      "url": "https://mangafire.to/read/holiday-yasumis-twitter-shortss.ppkq9/en/chapter-323"
    },
    {
      "number": "318",
      "title": "Chap 318",
      "url": "https://mangafire.to/read/holiday-yasumis-twitter-shortss.ppkq9/en/chapter-318"
    },
    {
      "number": "315",
      "title": "Chap 315",
      "url": "https://mangafire.to/read/holiday-yasumis-twitter-shortss.ppkq9/en/chapter-315"
    },
    {
      "number": "313",
      "title": "Chap 313",
      "url": "https://mangafire.to/read/holiday-yasumis-twitter-shortss.ppkq9/en/chapter-313"
    },
    {
      "number": "311",
      "title": "Chap 311",
      "url": "https://mangafire.to/read/holiday-yasumis-twitter-shortss.ppkq9/en/chapter-311"
    },
    {
      "number": "310",
      "title": "Chap 310",
      "url": "https://mangafire.to/read/holiday-yasumis-twitter-shortss.ppkq9/en/chapter-310"
    },
    {
      "number": "309",
      "title": "Chap 309",
      "url": "https://mangafire.to/read/holiday-yasumis-twitter-shortss.ppkq9/en/chapter-309"
    },
    {
      "number": "308",
      "title": "Chap 308",
      "url": "https://mangafire.to/read/holiday-yasumis-twitter-shortss.ppkq9/en/chapter-308"
    },
    {
      "number": "303",
      "title": "Chap 303",
      "url": "https://mangafire.to/read/holiday-yasumis-twitter-shortss.ppkq9/en/chapter-303"
    },
    {
      "number": "302",
      "title": "Chap 302",
      "url": "https://mangafire.to/read/holiday-yasumis-twitter-shortss.ppkq9/en/chapter-302"
    },
    {
      "number": "301",
      "title": "Chap 301",
      "url": "https://mangafire.to/read/holiday-yasumis-twitter-shortss.ppkq9/en/chapter-301"
    },
    {
      "number": "300",
      "title": "Chap 300",
      "url": "https://mangafire.to/read/holiday-yasumis-twitter-shortss.ppkq9/en/chapter-300"
    },
    {
      "number": "299",
      "title": "Chap 299",
      "url": "https://mangafire.to/read/holiday-yasumis-twitter-shortss.ppkq9/en/chapter-299"
    },
    {
      "number": "298",
      "title": "Chap 298",
      "url": "https://mangafire.to/read/holiday-yasumis-twitter-shortss.ppkq9/en/chapter-298"
    },
    {
      "number": "296",
      "title": "Chap 296",
      "url": "https://mangafire.to/read/holiday-yasumis-twitter-shortss.ppkq9/en/chapter-296"
    },
    {
      "number": "293",
      "title": "Chap 293",
      "url": "https://mangafire.to/read/holiday-yasumis-twitter-shortss.ppkq9/en/chapter-293"
    },
    {
      "number": "292",
      "title": "Chap 292",
      "url": "https://mangafire.to/read/holiday-yasumis-twitter-shortss.ppkq9/en/chapter-292"
    },
    {
      "number": "289",
      "title": "Chap 289",
      "url": "https://mangafire.to/read/holiday-yasumis-twitter-shortss.ppkq9/en/chapter-289"
    },
    {
      "number": "288",
      "title": "Chap 288",
      "url": "https://mangafire.to/read/holiday-yasumis-twitter-shortss.ppkq9/en/chapter-288"
    },
    {
      "number": "286",
      "title": "Chap 286",
      "url": "https://mangafire.to/read/holiday-yasumis-twitter-shortss.ppkq9/en/chapter-286"
    },
    {
      "number": "285",
      "title": "Chap 285",
      "url": "https://mangafire.to/read/holiday-yasumis-twitter-shortss.ppkq9/en/chapter-285"
    },
    {
      "number": "284",
      "title": "Chap 284",
      "url": "https://mangafire.to/read/holiday-yasumis-twitter-shortss.ppkq9/en/chapter-284"
    },
    {
      "number": "282",
      "title": "Chap 282",
      "url": "https://mangafire.to/read/holiday-yasumis-twitter-shortss.ppkq9/en/chapter-282"
    },
    {
      "number": "280",
      "title": "Chap 280",
      "url": "https://mangafire.to/read/holiday-yasumis-twitter-shortss.ppkq9/en/chapter-280"
    },
    {
      "number": "277",
      "title": "Chap 277",
      "url": "https://mangafire.to/read/holiday-yasumis-twitter-shortss.ppkq9/en/chapter-277"
    },
    {
      "number": "275",
      "title": "Chap 275",
      "url": "https://mangafire.to/read/holiday-yasumis-twitter-shortss.ppkq9/en/chapter-275"
    },
    {
      "number": "274",
      "title": "Chap 274",
      "url": "https://mangafire.to/read/holiday-yasumis-twitter-shortss.ppkq9/en/chapter-274"
    },
    {
      "number": "273",
      "title": "Chap 273",
      "url": "https://mangafire.to/read/holiday-yasumis-twitter-shortss.ppkq9/en/chapter-273"
    },
    {
      "number": "272",
      "title": "Chap 272",
      "url": "https://mangafire.to/read/holiday-yasumis-twitter-shortss.ppkq9/en/chapter-272"
    },
    {
      "number": "271",
      "title": "Chap 271",
      "url": "https://mangafire.to/read/holiday-yasumis-twitter-shortss.ppkq9/en/chapter-271"
    },
    {
      "number": "268",
      "title": "Chap 268",
      "url": "https://mangafire.to/read/holiday-yasumis-twitter-shortss.ppkq9/en/chapter-268"
    },
    {
      "number": "267",
      "title": "Chap 267",
      "url": "https://mangafire.to/read/holiday-yasumis-twitter-shortss.ppkq9/en/chapter-267"
    },
    {
      "number": "260",
      "title": "Chap 260",
      "url": "https://mangafire.to/read/holiday-yasumis-twitter-shortss.ppkq9/en/chapter-260"
    },
    {
      "number": "248",
      "title": "Chap 248",
      "url": "https://mangafire.to/read/holiday-yasumis-twitter-shortss.ppkq9/en/chapter-248"
    },
    {
      "number": "247",
      "title": "Chap 247",
      "url": "https://mangafire.to/read/holiday-yasumis-twitter-shortss.ppkq9/en/chapter-247"
    },
    {
      "number": "243",
      "title": "Chap 243",
      "url": "https://mangafire.to/read/holiday-yasumis-twitter-shortss.ppkq9/en/chapter-243"
    },
    {
      "number": "242",
      "title": "Chap 242",
      "url": "https://mangafire.to/read/holiday-yasumis-twitter-shortss.ppkq9/en/chapter-242"
    },
    {
      "number": "241",
      "title": "Chap 241",
      "url": "https://mangafire.to/read/holiday-yasumis-twitter-shortss.ppkq9/en/chapter-241"
    },
    {
      "number": "238",
      "title": "Chap 238",
      "url": "https://mangafire.to/read/holiday-yasumis-twitter-shortss.ppkq9/en/chapter-238"
    },
    {
      "number": "237",
      "title": "Chap 237",
      "url": "https://mangafire.to/read/holiday-yasumis-twitter-shortss.ppkq9/en/chapter-237"
    },
    {
      "number": "235",
      "title": "Chap 235",
      "url": "https://mangafire.to/read/holiday-yasumis-twitter-shortss.ppkq9/en/chapter-235"
    },
    {
      "number": "234",
      "title": "Chap 234",
      "url": "https://mangafire.to/read/holiday-yasumis-twitter-shortss.ppkq9/en/chapter-234"
    },
    {
      "number": "233",
      "title": "Chap 233",
      "url": "https://mangafire.to/read/holiday-yasumis-twitter-shortss.ppkq9/en/chapter-233"
    },
    {
      "number": "219",
      "title": "Chap 219",
      "url": "https://mangafire.to/read/holiday-yasumis-twitter-shortss.ppkq9/en/chapter-219"
    },
    {
      "number": "218",
      "title": "Chap 218",
      "url": "https://mangafire.to/read/holiday-yasumis-twitter-shortss.ppkq9/en/chapter-218"
    },
    {
      "number": "212",
      "title": "Chap 212",
      "url": "https://mangafire.to/read/holiday-yasumis-twitter-shortss.ppkq9/en/chapter-212"
    },
    {
      "number": "210",
      "title": "Chap 210",
      "url": "https://mangafire.to/read/holiday-yasumis-twitter-shortss.ppkq9/en/chapter-210"
    },
    {
      "number": "205",
      "title": "Chap 205",
      "url": "https://mangafire.to/read/holiday-yasumis-twitter-shortss.ppkq9/en/chapter-205"
    },
    {
      "number": "204",
      "title": "Chap 204",
      "url": "https://mangafire.to/read/holiday-yasumis-twitter-shortss.ppkq9/en/chapter-204"
    },
    {
      "number": "199",
      "title": "Chap 199",
      "url": "https://mangafire.to/read/holiday-yasumis-twitter-shortss.ppkq9/en/chapter-199"
    },
    {
      "number": "198",
      "title": "Chap 198",
      "url": "https://mangafire.to/read/holiday-yasumis-twitter-shortss.ppkq9/en/chapter-198"
    },
    {
      "number": "197",
      "title": "Chap 197",
      "url": "https://mangafire.to/read/holiday-yasumis-twitter-shortss.ppkq9/en/chapter-197"
    },
    {
      "number": "192",
      "title": "Chap 192",
      "url": "https://mangafire.to/read/holiday-yasumis-twitter-shortss.ppkq9/en/chapter-192"
    },
    {
      "number": "191",
      "title": "Chap 191",
      "url": "https://mangafire.to/read/holiday-yasumis-twitter-shortss.ppkq9/en/chapter-191"
    },
    {
      "number": "190",
      "title": "Chap 190",
      "url": "https://mangafire.to/read/holiday-yasumis-twitter-shortss.ppkq9/en/chapter-190"
    },
    {
      "number": "189",
      "title": "Chap 189",
      "url": "https://mangafire.to/read/holiday-yasumis-twitter-shortss.ppkq9/en/chapter-189"
    },
    {
      "number": "187",
      "title": "Chap 187",
      "url": "https://mangafire.to/read/holiday-yasumis-twitter-shortss.ppkq9/en/chapter-187"
    },
    {
      "number": "186",
      "title": "Chap 186",
      "url": "https://mangafire.to/read/holiday-yasumis-twitter-shortss.ppkq9/en/chapter-186"
    },
    {
      "number": "184",
      "title": "Chap 184",
      "url": "https://mangafire.to/read/holiday-yasumis-twitter-shortss.ppkq9/en/chapter-184"
    },
    {
      "number": "183",
      "title": "Chap 183",
      "url": "https://mangafire.to/read/holiday-yasumis-twitter-shortss.ppkq9/en/chapter-183"
    },
    {
      "number": "182",
      "title": "Chap 182",
      "url": "https://mangafire.to/read/holiday-yasumis-twitter-shortss.ppkq9/en/chapter-182"
    },
    {
      "number": "178",
      "title": "Chap 178",
      "url": "https://mangafire.to/read/holiday-yasumis-twitter-shortss.ppkq9/en/chapter-178"
    },
    {
      "number": "174",
      "title": "Chap 174",
      "url": "https://mangafire.to/read/holiday-yasumis-twitter-shortss.ppkq9/en/chapter-174"
    },
    {
      "number": "173",
      "title": "Chap 173",
      "url": "https://mangafire.to/read/holiday-yasumis-twitter-shortss.ppkq9/en/chapter-173"
    },
    {
      "number": "171",
      "title": "Chap 171",
      "url": "https://mangafire.to/read/holiday-yasumis-twitter-shortss.ppkq9/en/chapter-171"
    },
    {
      "number": "170",
      "title": "Chap 170",
      "url": "https://mangafire.to/read/holiday-yasumis-twitter-shortss.ppkq9/en/chapter-170"
    },
    {
      "number": "167",
      "title": "Chap 167",
      "url": "https://mangafire.to/read/holiday-yasumis-twitter-shortss.ppkq9/en/chapter-167"
    },
    {
      "number": "166",
      "title": "Chap 166",
      "url": "https://mangafire.to/read/holiday-yasumis-twitter-shortss.ppkq9/en/chapter-166"
    },
    {
      "number": "165",
      "title": "Chap 165",
      "url": "https://mangafire.to/read/holiday-yasumis-twitter-shortss.ppkq9/en/chapter-165"
    },
    {
      "number": "164",
      "title": "Chap 164",
      "url": "https://mangafire.to/read/holiday-yasumis-twitter-shortss.ppkq9/en/chapter-164"
    },
    {
      "number": "161",
      "title": "Chap 161",
      "url": "https://mangafire.to/read/holiday-yasumis-twitter-shortss.ppkq9/en/chapter-161"
    },
    {
      "number": "159",
      "title": "Chap 159",
      "url": "https://mangafire.to/read/holiday-yasumis-twitter-shortss.ppkq9/en/chapter-159"
    },
    {
      "number": "154",
      "title": "Chap 154",
      "url": "https://mangafire.to/read/holiday-yasumis-twitter-shortss.ppkq9/en/chapter-154"
    },
    {
      "number": "152",
      "title": "Chap 152",
      "url": "https://mangafire.to/read/holiday-yasumis-twitter-shortss.ppkq9/en/chapter-152"
    },
    {
      "number": "149",
      "title": "Chap 149",
      "url": "https://mangafire.to/read/holiday-yasumis-twitter-shortss.ppkq9/en/chapter-149"
    },
    {
      "number": "148",
      "title": "Chap 148",
      "url": "https://mangafire.to/read/holiday-yasumis-twitter-shortss.ppkq9/en/chapter-148"
    },
    {
      "number": "145",
      "title": "Chap 145",
      "url": "https://mangafire.to/read/holiday-yasumis-twitter-shortss.ppkq9/en/chapter-145"
    },
    {
      "number": "144",
      "title": "Chap 144",
      "url": "https://mangafire.to/read/holiday-yasumis-twitter-shortss.ppkq9/en/chapter-144"
    },
    {
      "number": "143",
      "title": "Chap 143",
      "url": "https://mangafire.to/read/holiday-yasumis-twitter-shortss.ppkq9/en/chapter-143"
    },
    {
      "number": "140",
      "title": "Chap 140",
      "url": "https://mangafire.to/read/holiday-yasumis-twitter-shortss.ppkq9/en/chapter-140"
    },
    {
      "number": "139",
      "title": "Chap 139",
      "url": "https://mangafire.to/read/holiday-yasumis-twitter-shortss.ppkq9/en/chapter-139"
    },
    {
      "number": "136",
      "title": "Chap 136",
      "url": "https://mangafire.to/read/holiday-yasumis-twitter-shortss.ppkq9/en/chapter-136"
    },
    {
      "number": "134",
      "title": "Chap 134",
      "url": "https://mangafire.to/read/holiday-yasumis-twitter-shortss.ppkq9/en/chapter-134"
    },
    {
      "number": "133",
      "title": "Chap 133",
      "url": "https://mangafire.to/read/holiday-yasumis-twitter-shortss.ppkq9/en/chapter-133"
    },
    {
      "number": "128",
      "title": "Chap 128",
      "url": "https://mangafire.to/read/holiday-yasumis-twitter-shortss.ppkq9/en/chapter-128"
    },
    {
      "number": "122",
      "title": "Chap 122",
      "url": "https://mangafire.to/read/holiday-yasumis-twitter-shortss.ppkq9/en/chapter-122"
    },
    {
      "number": "120",
      "title": "Chap 120",
      "url": "https://mangafire.to/read/holiday-yasumis-twitter-shortss.ppkq9/en/chapter-120"
    },
    {
      "number": "118",
      "title": "Chap 118",
      "url": "https://mangafire.to/read/holiday-yasumis-twitter-shortss.ppkq9/en/chapter-118"
    },
    {
      "number": "113",
      "title": "Chap 113",
      "url": "https://mangafire.to/read/holiday-yasumis-twitter-shortss.ppkq9/en/chapter-113"
    },
    {
      "number": "111",
      "title": "Chap 111",
      "url": "https://mangafire.to/read/holiday-yasumis-twitter-shortss.ppkq9/en/chapter-111"
    },
    {
      "number": "108",
      "title": "Chap 108",
      "url": "https://mangafire.to/read/holiday-yasumis-twitter-shortss.ppkq9/en/chapter-108"
    },
    {
      "number": "107",
      "title": "Chap 107",
      "url": "https://mangafire.to/read/holiday-yasumis-twitter-shortss.ppkq9/en/chapter-107"
    },
    {
      "number": "106",
      "title": "Chap 106",
      "url": "https://mangafire.to/read/holiday-yasumis-twitter-shortss.ppkq9/en/chapter-106"
    },
    {
      "number": "105",
      "title": "Chap 105",
      "url": "https://mangafire.to/read/holiday-yasumis-twitter-shortss.ppkq9/en/chapter-105"
    },
    {
      "number": "104",
      "title": "Chap 104",
      "url": "https://mangafire.to/read/holiday-yasumis-twitter-shortss.ppkq9/en/chapter-104"
    },
    {
      "number": "102",
      "title": "Chap 102",
      "url": "https://mangafire.to/read/holiday-yasumis-twitter-shortss.ppkq9/en/chapter-102"
    },
    {
      "number": "101",
      "title": "Chap 101",
      "url": "https://mangafire.to/read/holiday-yasumis-twitter-shortss.ppkq9/en/chapter-101"
    },
    {
      "number": "100",
      "title": "Chap 100",
      "url": "https://mangafire.to/read/holiday-yasumis-twitter-shortss.ppkq9/en/chapter-100"
    },
    {
      "number": "99",
      "title": "Chap 99",
      "url": "https://mangafire.to/read/holiday-yasumis-twitter-shortss.ppkq9/en/chapter-99"
    },
    {
      "number": "98",
      "title": "Chap 98",
      "url": "https://mangafire.to/read/holiday-yasumis-twitter-shortss.ppkq9/en/chapter-98"
    },
    {
      "number": "97",
      "title": "Chap 97",
      "url": "https://mangafire.to/read/holiday-yasumis-twitter-shortss.ppkq9/en/chapter-97"
    },
    {
      "number": "96",
      "title": "Chap 96",
      "url": "https://mangafire.to/read/holiday-yasumis-twitter-shortss.ppkq9/en/chapter-96"
    },
    {
      "number": "95",
      "title": "Chap 95",
      "url": "https://mangafire.to/read/holiday-yasumis-twitter-shortss.ppkq9/en/chapter-95"
    },
    {
      "number": "92",
      "title": "Chap 92",
      "url": "https://mangafire.to/read/holiday-yasumis-twitter-shortss.ppkq9/en/chapter-92"
    },
    {
      "number": "91",
      "title": "Chap 91",
      "url": "https://mangafire.to/read/holiday-yasumis-twitter-shortss.ppkq9/en/chapter-91"
    },
    {
      "number": "86",
      "title": "Chap 86",
      "url": "https://mangafire.to/read/holiday-yasumis-twitter-shortss.ppkq9/en/chapter-86"
    },
    {
      "number": "85",
      "title": "Chap 85",
      "url": "https://mangafire.to/read/holiday-yasumis-twitter-shortss.ppkq9/en/chapter-85"
    },
    {
      "number": "84",
      "title": "Chap 84",
      "url": "https://mangafire.to/read/holiday-yasumis-twitter-shortss.ppkq9/en/chapter-84"
    },
    {
      "number": "81",
      "title": "Chap 81",
      "url": "https://mangafire.to/read/holiday-yasumis-twitter-shortss.ppkq9/en/chapter-81"
    },
    {
      "number": "80",
      "title": "Chap 80",
      "url": "https://mangafire.to/read/holiday-yasumis-twitter-shortss.ppkq9/en/chapter-80"
    },
    {
      "number": "79",
      "title": "Chap 79",
      "url": "https://mangafire.to/read/holiday-yasumis-twitter-shortss.ppkq9/en/chapter-79"
    },
    {
      "number": "78",
      "title": "Chap 78",
      "url": "https://mangafire.to/read/holiday-yasumis-twitter-shortss.ppkq9/en/chapter-78"
    },
    {
      "number": "76",
      "title": "Chap 76",
      "url": "https://mangafire.to/read/holiday-yasumis-twitter-shortss.ppkq9/en/chapter-76"
    },
    {
      "number": "75",
      "title": "Chap 75",
      "url": "https://mangafire.to/read/holiday-yasumis-twitter-shortss.ppkq9/en/chapter-75"
    },
    {
      "number": "74",
      "title": "Chap 74",
      "url": "https://mangafire.to/read/holiday-yasumis-twitter-shortss.ppkq9/en/chapter-74"
    },
    {
      "number": "73",
      "title": "Chap 73",
      "url": "https://mangafire.to/read/holiday-yasumis-twitter-shortss.ppkq9/en/chapter-73"
    },
    {
      "number": "72",
      "title": "Chap 72",
      "url": "https://mangafire.to/read/holiday-yasumis-twitter-shortss.ppkq9/en/chapter-72"
    },
    {
      "number": "71",
      "title": "Chap 71",
      "url": "https://mangafire.to/read/holiday-yasumis-twitter-shortss.ppkq9/en/chapter-71"
    },
    {
      "number": "70",
      "title": "Chap 70",
      "url": "https://mangafire.to/read/holiday-yasumis-twitter-shortss.ppkq9/en/chapter-70"
    },
    {
      "number": "69",
      "title": "Chap 69",
      "url": "https://mangafire.to/read/holiday-yasumis-twitter-shortss.ppkq9/en/chapter-69"
    },
    {
      "number": "68",
      "title": "Chap 68",
      "url": "https://mangafire.to/read/holiday-yasumis-twitter-shortss.ppkq9/en/chapter-68"
    },
    {
      "number": "67",
      "title": "Chap 67",
      "url": "https://mangafire.to/read/holiday-yasumis-twitter-shortss.ppkq9/en/chapter-67"
    },
    {
      "number": "66",
      "title": "Chap 66",
      "url": "https://mangafire.to/read/holiday-yasumis-twitter-shortss.ppkq9/en/chapter-66"
    },
    {
      "number": "65",
      "title": "Chap 65",
      "url": "https://mangafire.to/read/holiday-yasumis-twitter-shortss.ppkq9/en/chapter-65"
    },
    {
      "number": "64",
      "title": "Chap 64",
      "url": "https://mangafire.to/read/holiday-yasumis-twitter-shortss.ppkq9/en/chapter-64"
    },
    {
      "number": "63",
      "title": "Chap 63",
      "url": "https://mangafire.to/read/holiday-yasumis-twitter-shortss.ppkq9/en/chapter-63"
    },
    {
      "number": "62",
      "title": "Chap 62",
      "url": "https://mangafire.to/read/holiday-yasumis-twitter-shortss.ppkq9/en/chapter-62"
    },
    {
      "number": "61",
      "title": "Chap 61",
      "url": "https://mangafire.to/read/holiday-yasumis-twitter-shortss.ppkq9/en/chapter-61"
    },
    {
      "number": "60",
      "title": "Chap 60",
      "url": "https://mangafire.to/read/holiday-yasumis-twitter-shortss.ppkq9/en/chapter-60"
    },
    {
      "number": "59",
      "title": "Chap 59",
      "url": "https://mangafire.to/read/holiday-yasumis-twitter-shortss.ppkq9/en/chapter-59"
    },
    {
      "number": "58",
      "title": "Chap 58",
      "url": "https://mangafire.to/read/holiday-yasumis-twitter-shortss.ppkq9/en/chapter-58"
    },
    {
      "number": "57",
      "title": "Chap 57",
      "url": "https://mangafire.to/read/holiday-yasumis-twitter-shortss.ppkq9/en/chapter-57"
    },
    {
      "number": "56",
      "title": "Chap 56",
      "url": "https://mangafire.to/read/holiday-yasumis-twitter-shortss.ppkq9/en/chapter-56"
    },
    {
      "number": "54",
      "title": "Chap 54",
      "url": "https://mangafire.to/read/holiday-yasumis-twitter-shortss.ppkq9/en/chapter-54"
    },
    {
      "number": "51",
      "title": "Chap 51",
      "url": "https://mangafire.to/read/holiday-yasumis-twitter-shortss.ppkq9/en/chapter-51"
    },
    {
      "number": "49",
      "title": "Chap 49",
      "url": "https://mangafire.to/read/holiday-yasumis-twitter-shortss.ppkq9/en/chapter-49"
    },
    {
      "number": "45",
      "title": "Chap 45",
      "url": "https://mangafire.to/read/holiday-yasumis-twitter-shortss.ppkq9/en/chapter-45"
    },
    {
      "number": "43",
      "title": "Chap 43",
      "url": "https://mangafire.to/read/holiday-yasumis-twitter-shortss.ppkq9/en/chapter-43"
    },
    {
      "number": "40",
      "title": "Chap 40",
      "url": "https://mangafire.to/read/holiday-yasumis-twitter-shortss.ppkq9/en/chapter-40"
    },
    {
      "number": "39",
      "title": "Chap 39",
      "url": "https://mangafire.to/read/holiday-yasumis-twitter-shortss.ppkq9/en/chapter-39"
    },
    {
      "number": "35",
      "title": "Chap 35",
      "url": "https://mangafire.to/read/holiday-yasumis-twitter-shortss.ppkq9/en/chapter-35"
    },
    {
      "number": "30",
      "title": "Chap 30",
      "url": "https://mangafire.to/read/holiday-yasumis-twitter-shortss.ppkq9/en/chapter-30"
    },
    {
      "number": "28",
      "title": "Chap 28",
      "url": "https://mangafire.to/read/holiday-yasumis-twitter-shortss.ppkq9/en/chapter-28"
    },
    {
      "number": "27",
      "title": "Chap 27",
      "url": "https://mangafire.to/read/holiday-yasumis-twitter-shortss.ppkq9/en/chapter-27"
    },
    {
      "number": "25",
      "title": "Chap 25",
      "url": "https://mangafire.to/read/holiday-yasumis-twitter-shortss.ppkq9/en/chapter-25"
    },
    {
      "number": "0",
      "title": "Chap 0",
      "url": "https://mangafire.to/read/holiday-yasumis-twitter-shortss.ppkq9/en/chapter-0"
    }
  ]
}