{
  "slug": "kiitarou-shounen-no-youkai-enikkii.3rzqr",
  "title": "Kiitarou Shounen no Youkai Enikki",
  "cover": "https://static.mfcdn.nl/d21a/i/0/00/000e922756876b46cc2b0074b314c5ca@100.jpg",
  "description": "Kiitarou Shounen no Youkai Enikki manga, read all chapters here, the latest chapter 2 is available. Read Kiitarou Shounen no Youkai Enikki raw, multiple language. READ NOW!!",
  "status": "Releasing",
  "genres": [
    "Action",
    "Adventure",
    "Avant Garde",
    "Boys Love",
    "Comedy",
    "Demons",
    "Drama",
    "Ecchi",
    "Fantasy",
    "Girls Love",
    "Gourmet",
    "Harem",
    "Horror",
    "Isekai",
    "Iyashikei",
    "Josei",
    "Kids",
    "Magic",
    "Mahou Shoujo",
    "Martial Arts",
    "Mecha",
    "Military",
    "Music",
    "Mystery",
    "Parody",
    "Psychological",
    "Reverse Harem",
    "Romance",
    "School",
    "Sci-Fi",
    "Seinen",
    "Shoujo",
    "Shounen",
    "Slice of Life",
    "Space",
    "Sports",
    "Super Power",
    "Supernatural",
    "Suspense",
    "Thriller",
    "Vampire",
    "Comedy",
    "Supernatural"
  ],
  "chapters": [
    {
      "number": "2",
      "title": "Chap 2",
      "url": "https://mangafire.to/read/kiitarou-shounen-no-youkai-enikkii.3rzqr/en/chapter-2"
    },
    {
      "number": "1",
      "title": "Chap 1",
      "url": "https://mangafire.to/read/kiitarou-shounen-no-youkai-enikkii.3rzqr/en/chapter-1"
    }
  ],
  "fetched_at": "2026-04-27T03:18:31Z"
}