{
  "slug": "kirawaremono-no-akuyaku-reisoku-ni-tensei-shita-no-ni-naze-ka-mawari-ga-hanatte-oite-kurenaii.rwzqo",
  "title": "Kirawaremono no Akuyaku Reisoku ni Tensei shita no ni, Naze ka Mawari ga Hanatte Oite Kurenai",
  "cover": "https://static.mfcdn.nl/42c7/i/0/04/04fbee1d422e85756f15744320cf8de1@100.jpg",
  "description": "Kirawaremono no Akuyaku Reisoku ni Tensei shita no ni, Naze ka Mawari ga Hanatte Oite Kurenai manga, read all chapters here, the latest chapter 11 is available. Read Kirawaremono no Akuyaku Reisoku ni Tensei shita no ni, Naze ka Mawari ga Hanatte Oite Kurenai raw, multiple language. READ NOW!!",
  "status": "Releasing",
  "genres": [
    "Action",
    "Adventure",
    "Avant Garde",
    "Boys Love",
    "Comedy",
    "Demons",
    "Drama",
    "Ecchi",
    "Fantasy",
    "Girls Love",
    "Gourmet",
    "Harem",
    "Horror",
    "Isekai",
    "Iyashikei",
    "Josei",
    "Kids",
    "Magic",
    "Mahou Shoujo",
    "Martial Arts",
    "Mecha",
    "Military",
    "Music",
    "Mystery",
    "Parody",
    "Psychological",
    "Reverse Harem",
    "Romance",
    "School",
    "Sci-Fi",
    "Seinen",
    "Shoujo",
    "Shounen",
    "Slice of Life",
    "Space",
    "Sports",
    "Super Power",
    "Supernatural",
    "Suspense",
    "Thriller",
    "Vampire",
    "Action",
    "Fantasy",
    "Seinen"
  ],
  "chapters": [
    {
      "number": "7",
      "title": "Vol 2 -  Chap 7",
      "url": "https://mangafire.to/read/kirawaremono-no-akuyaku-reisoku-ni-tensei-shita-no-ni-naze-ka-mawari-ga-hanatte-oite-kurenaii.rwzqo/en/chapter-7"
    },
    {
      "number": "6",
      "title": "Vol 1 -  Chap 6",
      "url": "https://mangafire.to/read/kirawaremono-no-akuyaku-reisoku-ni-tensei-shita-no-ni-naze-ka-mawari-ga-hanatte-oite-kurenaii.rwzqo/en/chapter-6"
    },
    {
      "number": "5",
      "title": "Vol 1 -  Chap 5",
      "url": "https://mangafire.to/read/kirawaremono-no-akuyaku-reisoku-ni-tensei-shita-no-ni-naze-ka-mawari-ga-hanatte-oite-kurenaii.rwzqo/en/chapter-5"
    },
    {
      "number": "4",
      "title": "Vol 1 -  Chap 4",
      "url": "https://mangafire.to/read/kirawaremono-no-akuyaku-reisoku-ni-tensei-shita-no-ni-naze-ka-mawari-ga-hanatte-oite-kurenaii.rwzqo/en/chapter-4"
    },
    {
      "number": "3",
      "title": "Vol 1 -  Chap 3",
      "url": "https://mangafire.to/read/kirawaremono-no-akuyaku-reisoku-ni-tensei-shita-no-ni-naze-ka-mawari-ga-hanatte-oite-kurenaii.rwzqo/en/chapter-3"
    },
    {
      "number": "2",
      "title": "Vol 1 -  Chap 2",
      "url": "https://mangafire.to/read/kirawaremono-no-akuyaku-reisoku-ni-tensei-shita-no-ni-naze-ka-mawari-ga-hanatte-oite-kurenaii.rwzqo/en/chapter-2"
    },
    {
      "number": "1",
      "title": "Vol 1 -  Chap 1",
      "url": "https://mangafire.to/read/kirawaremono-no-akuyaku-reisoku-ni-tensei-shita-no-ni-naze-ka-mawari-ga-hanatte-oite-kurenaii.rwzqo/en/chapter-1"
    }
  ]
}