{
  "slug": "kyoukai-no-shinigamii.z75l",
  "title": "In the Mirror of Death",
  "cover": "https://static.mfcdn.nl/26b1/i/9/9d/9da443891764aa5524901d7c7a9865f6@100.jpg",
  "description": "In the Mirror of Death manga, read all chapters here, the latest chapter 0 is available. Read In the Mirror of Death raw, multiple language. READ NOW!!",
  "status": "Completed",
  "genres": [
    "Action",
    "Adventure",
    "Avant Garde",
    "Boys Love",
    "Comedy",
    "Demons",
    "Drama",
    "Ecchi",
    "Fantasy",
    "Girls Love",
    "Gourmet",
    "Harem",
    "Horror",
    "Isekai",
    "Iyashikei",
    "Josei",
    "Kids",
    "Magic",
    "Mahou Shoujo",
    "Martial Arts",
    "Mecha",
    "Military",
    "Music",
    "Mystery",
    "Parody",
    "Psychological",
    "Reverse Harem",
    "Romance",
    "School",
    "Sci-Fi",
    "Seinen",
    "Shoujo",
    "Shounen",
    "Slice of Life",
    "Space",
    "Sports",
    "Super Power",
    "Supernatural",
    "Suspense",
    "Thriller",
    "Vampire",
    "Drama",
    "Romance",
    "Shoujo",
    "School",
    "Horror"
  ],
  "chapters": [
    {
      "number": "0",
      "title": "Chap 0",
      "url": "https://mangafire.to/read/kyoukai-no-shinigamii.z75l/en/chapter-0"
    }
  ],
  "fetched_at": "2026-04-27T08:11:01Z"
}