{
  "slug": "meitantei-conan-dj-utsukushii-ao-wa-ima-mo-koko-de-kagayaite-iruu.v94n6",
  "title": "Meitantei Conan dj - Utsukushii Ao wa Ima mo Koko de Kagayaite Iru",
  "cover": "https://static.mfcdn.nl/3aa9/i/9/95/da60f7045a1a04bbde01520eb24c793e@100.jpg",
  "description": "Meitantei Conan dj - Utsukushii Ao wa Ima mo Koko de Kagayaite Iru manga, read all chapters here, the latest chapter 0 is available. Read Meitantei Conan dj - Utsukushii Ao wa Ima mo Koko de Kagayaite Iru raw, multiple language. READ NOW!!",
  "status": "Completed",
  "genres": [
    "Action",
    "Adventure",
    "Avant Garde",
    "Boys Love",
    "Comedy",
    "Demons",
    "Drama",
    "Ecchi",
    "Fantasy",
    "Girls Love",
    "Gourmet",
    "Harem",
    "Horror",
    "Isekai",
    "Iyashikei",
    "Josei",
    "Kids",
    "Magic",
    "Mahou Shoujo",
    "Martial Arts",
    "Mecha",
    "Military",
    "Music",
    "Mystery",
    "Parody",
    "Psychological",
    "Reverse Harem",
    "Romance",
    "School",
    "Sci-Fi",
    "Seinen",
    "Shoujo",
    "Shounen",
    "Slice of Life",
    "Space",
    "Sports",
    "Super Power",
    "Supernatural",
    "Suspense",
    "Thriller",
    "Vampire",
    "Boys Love",
    "Romance",
    "Slice of Life"
  ],
  "chapters": [
    {
      "number": "0",
      "title": "Chap 0",
      "url": "https://mangafire.to/read/meitantei-conan-dj-utsukushii-ao-wa-ima-mo-koko-de-kagayaite-iruu.v94n6/en/chapter-0"
    }
  ],
  "fetched_at": "2026-04-27T08:48:50Z"
}