{
  "slug": "my-god-i-have-transformed-into-the-turtle.zxokm",
  "title": "My God! I Have Transformed Into the Turtle",
  "cover": "https://static.mfcdn.nl/1f9f/i/e/e2/e2003b7959c9fbea20ba65519d6e41de@100.jpg",
  "description": "My God! I Have Transformed Into the Turtle manga, read all chapters here, the latest chapter 1 is available. Read My God! I Have Transformed Into the Turtle raw, multiple language. READ NOW!!",
  "status": "Releasing",
  "genres": [
    "Action",
    "Adventure",
    "Avant Garde",
    "Boys Love",
    "Comedy",
    "Demons",
    "Drama",
    "Ecchi",
    "Fantasy",
    "Girls Love",
    "Gourmet",
    "Harem",
    "Horror",
    "Isekai",
    "Iyashikei",
    "Josei",
    "Kids",
    "Magic",
    "Mahou Shoujo",
    "Martial Arts",
    "Mecha",
    "Military",
    "Music",
    "Mystery",
    "Parody",
    "Psychological",
    "Reverse Harem",
    "Romance",
    "School",
    "Sci-Fi",
    "Seinen",
    "Shoujo",
    "Shounen",
    "Slice of Life",
    "Space",
    "Sports",
    "Super Power",
    "Supernatural",
    "Suspense",
    "Thriller",
    "Vampire",
    "Action",
    "Drama",
    "Fantasy"
  ],
  "chapters": [
    {
      "number": "1",
      "title": "Chap 1",
      "url": "https://mangafire.to/read/my-god-i-have-transformed-into-the-turtle.zxokm/en/chapter-1"
    }
  ]
}