{
  "slug": "naisho-no-mangaka-tonari-no-yutori-sann.yr5p",
  "title": "Naisho no Mangaka Tonari no Yutori-san",
  "cover": "https://static.mfcdn.nl/bf31/i/b/ba/ba449c8dc82484afa9311028382174ec@100.jpg",
  "description": "Naisho no Mangaka Tonari no Yutori-san manga, read all chapters here, the latest chapter 1 is available. Read Naisho no Mangaka Tonari no Yutori-san raw, multiple language. READ NOW!!",
  "status": "Releasing",
  "genres": [
    "Action",
    "Adventure",
    "Avant Garde",
    "Boys Love",
    "Comedy",
    "Demons",
    "Drama",
    "Ecchi",
    "Fantasy",
    "Girls Love",
    "Gourmet",
    "Harem",
    "Horror",
    "Isekai",
    "Iyashikei",
    "Josei",
    "Kids",
    "Magic",
    "Mahou Shoujo",
    "Martial Arts",
    "Mecha",
    "Military",
    "Music",
    "Mystery",
    "Parody",
    "Psychological",
    "Reverse Harem",
    "Romance",
    "School",
    "Sci-Fi",
    "Seinen",
    "Shoujo",
    "Shounen",
    "Slice of Life",
    "Space",
    "Sports",
    "Super Power",
    "Supernatural",
    "Suspense",
    "Thriller",
    "Vampire",
    "Comedy",
    "Romance",
    "Shounen"
  ],
  "chapters": [
    {
      "number": "1",
      "title": "Vol 1 -  Chap 1",
      "url": "https://mangafire.to/read/naisho-no-mangaka-tonari-no-yutori-sann.yr5p/en/chapter-1"
    }
  ]
}