{
  "slug": "namaiki-na-gyaru-ane-o-ore-no-houhou-de-wakaraseru-koto-ni-shita-hii.8xp9y",
  "title": "Namaiki na Gyaru Ane o Ore no Houhou de Wakaraseru koto ni shita Hi",
  "cover": "https://static.mfcdn.nl/f149/i/f/f4/f4b48fcd9c58423b40ade03b3dae5bc4@100.jpg",
  "description": "Namaiki na Gyaru Ane o Ore no Houhou de Wakaraseru koto ni shita Hi manga, read all chapters here, the latest chapter 5 is available. Read Namaiki na Gyaru Ane o Ore no Houhou de Wakaraseru koto ni shita Hi raw, multiple language. READ NOW!!",
  "status": "Completed",
  "genres": [
    "Action",
    "Adventure",
    "Avant Garde",
    "Boys Love",
    "Comedy",
    "Demons",
    "Drama",
    "Ecchi",
    "Fantasy",
    "Girls Love",
    "Gourmet",
    "Harem",
    "Horror",
    "Isekai",
    "Iyashikei",
    "Josei",
    "Kids",
    "Magic",
    "Mahou Shoujo",
    "Martial Arts",
    "Mecha",
    "Military",
    "Music",
    "Mystery",
    "Parody",
    "Psychological",
    "Reverse Harem",
    "Romance",
    "School",
    "Sci-Fi",
    "Seinen",
    "Shoujo",
    "Shounen",
    "Slice of Life",
    "Space",
    "Sports",
    "Super Power",
    "Supernatural",
    "Suspense",
    "Thriller",
    "Vampire",
    "Ecchi",
    "Slice of Life"
  ],
  "chapters": [
    {
      "number": "5",
      "title": "Chap 5",
      "url": "https://mangafire.to/read/namaiki-na-gyaru-ane-o-ore-no-houhou-de-wakaraseru-koto-ni-shita-hii.8xp9y/en/chapter-5"
    },
    {
      "number": "4",
      "title": "Chap 4",
      "url": "https://mangafire.to/read/namaiki-na-gyaru-ane-o-ore-no-houhou-de-wakaraseru-koto-ni-shita-hii.8xp9y/en/chapter-4"
    },
    {
      "number": "3",
      "title": "Chap 3",
      "url": "https://mangafire.to/read/namaiki-na-gyaru-ane-o-ore-no-houhou-de-wakaraseru-koto-ni-shita-hii.8xp9y/en/chapter-3"
    },
    {
      "number": "2",
      "title": "Chap 2",
      "url": "https://mangafire.to/read/namaiki-na-gyaru-ane-o-ore-no-houhou-de-wakaraseru-koto-ni-shita-hii.8xp9y/en/chapter-2"
    },
    {
      "number": "1",
      "title": "Chap 1",
      "url": "https://mangafire.to/read/namaiki-na-gyaru-ane-o-ore-no-houhou-de-wakaraseru-koto-ni-shita-hii.8xp9y/en/chapter-1"
    }
  ],
  "fetched_at": "2026-04-27T08:46:31Z"
}