{
  "slug": "naruto22.021y3",
  "title": "NARUTO",
  "cover": "https://static.mfcdn.nl/ddbc/i/d/dd/dd560047c5a8e682abca5138fc140b80@100.jpg",
  "description": "NARUTO manga, read all chapters here, the latest chapter 0 is available. Read NARUTO raw, multiple language. READ NOW!!",
  "status": "Completed",
  "genres": [
    "Action",
    "Adventure",
    "Avant Garde",
    "Boys Love",
    "Comedy",
    "Demons",
    "Drama",
    "Ecchi",
    "Fantasy",
    "Girls Love",
    "Gourmet",
    "Harem",
    "Horror",
    "Isekai",
    "Iyashikei",
    "Josei",
    "Kids",
    "Magic",
    "Mahou Shoujo",
    "Martial Arts",
    "Mecha",
    "Military",
    "Music",
    "Mystery",
    "Parody",
    "Psychological",
    "Reverse Harem",
    "Romance",
    "School",
    "Sci-Fi",
    "Seinen",
    "Shoujo",
    "Shounen",
    "Slice of Life",
    "Space",
    "Sports",
    "Super Power",
    "Supernatural",
    "Suspense",
    "Thriller",
    "Vampire",
    "Action",
    "Shounen",
    "Super Power"
  ],
  "chapters": [
    {
      "number": "0",
      "title": "Chap 0",
      "url": "https://mangafire.to/read/naruto22.021y3/en/chapter-0"
    }
  ],
  "fetched_at": "2026-04-27T07:11:23Z"
}