{
  "slug": "oshi-to-wa-chigauu.ykv8x",
  "title": "Oshi to wa Chigau!",
  "cover": "https://static.mfcdn.nl/f149/i/f/f4/f4b48fcd9c58423b40ade03b3dae5bc4@100.jpg",
  "description": "Oshi to wa Chigau! manga, read all chapters here, the latest chapter 1 is available. Read Oshi to wa Chigau! raw, multiple language. READ NOW!!",
  "status": "Completed",
  "genres": [
    "Action",
    "Adventure",
    "Avant Garde",
    "Boys Love",
    "Comedy",
    "Demons",
    "Drama",
    "Ecchi",
    "Fantasy",
    "Girls Love",
    "Gourmet",
    "Harem",
    "Horror",
    "Isekai",
    "Iyashikei",
    "Josei",
    "Kids",
    "Magic",
    "Mahou Shoujo",
    "Martial Arts",
    "Mecha",
    "Military",
    "Music",
    "Mystery",
    "Parody",
    "Psychological",
    "Reverse Harem",
    "Romance",
    "School",
    "Sci-Fi",
    "Seinen",
    "Shoujo",
    "Shounen",
    "Slice of Life",
    "Space",
    "Sports",
    "Super Power",
    "Supernatural",
    "Suspense",
    "Thriller",
    "Vampire",
    "Comedy",
    "Josei",
    "Slice of Life"
  ],
  "chapters": [
    {
      "number": "1",
      "title": "Chap 1",
      "url": "https://mangafire.to/read/oshi-to-wa-chigauu.ykv8x/en/chapter-1"
    }
  ],
  "fetched_at": "2026-04-27T03:02:12Z"
}