{
  "slug": "oyu-de-hokorobu-yukime-senpaii.372w2",
  "title": "Oyu de Hokorobu Yukime Senpai",
  "cover": "https://static.mfcdn.nl/b4c0/i/2/25/255552e96eca8693bc68c06b26f3c43f@100.jpg",
  "description": "Oyu de Hokorobu Yukime Senpai manga, read all chapters here, the latest chapter 3 is available. Read Oyu de Hokorobu Yukime Senpai raw, multiple language. READ NOW!!",
  "status": "Completed",
  "genres": [
    "Action",
    "Adventure",
    "Avant Garde",
    "Boys Love",
    "Comedy",
    "Demons",
    "Drama",
    "Ecchi",
    "Fantasy",
    "Girls Love",
    "Gourmet",
    "Harem",
    "Horror",
    "Isekai",
    "Iyashikei",
    "Josei",
    "Kids",
    "Magic",
    "Mahou Shoujo",
    "Martial Arts",
    "Mecha",
    "Military",
    "Music",
    "Mystery",
    "Parody",
    "Psychological",
    "Reverse Harem",
    "Romance",
    "School",
    "Sci-Fi",
    "Seinen",
    "Shoujo",
    "Shounen",
    "Slice of Life",
    "Space",
    "Sports",
    "Super Power",
    "Supernatural",
    "Suspense",
    "Thriller",
    "Vampire",
    "Comedy",
    "Ecchi",
    "Slice of Life"
  ],
  "chapters": [
    {
      "number": "3",
      "title": "Chap 3",
      "url": "https://mangafire.to/read/oyu-de-hokorobu-yukime-senpaii.372w2/en/chapter-3"
    },
    {
      "number": "2",
      "title": "Chap 2",
      "url": "https://mangafire.to/read/oyu-de-hokorobu-yukime-senpaii.372w2/en/chapter-2"
    },
    {
      "number": "1",
      "title": "Chap 1",
      "url": "https://mangafire.to/read/oyu-de-hokorobu-yukime-senpaii.372w2/en/chapter-1"
    }
  ],
  "fetched_at": "2026-04-27T01:36:47Z"
}