{
  "slug": "rec22.05o5",
  "title": "●REC",
  "cover": "https://static.mfcdn.nl/29bd/i/5/53/53eb02da1c570de76faeafb6807b2ef3@100.jpg",
  "description": "●REC manga, read all chapters here, the latest chapter 0 is available. Read ●REC raw, multiple language. READ NOW!!",
  "status": "Completed",
  "genres": [
    "Action",
    "Adventure",
    "Avant Garde",
    "Boys Love",
    "Comedy",
    "Demons",
    "Drama",
    "Ecchi",
    "Fantasy",
    "Girls Love",
    "Gourmet",
    "Harem",
    "Horror",
    "Isekai",
    "Iyashikei",
    "Josei",
    "Kids",
    "Magic",
    "Mahou Shoujo",
    "Martial Arts",
    "Mecha",
    "Military",
    "Music",
    "Mystery",
    "Parody",
    "Psychological",
    "Reverse Harem",
    "Romance",
    "School",
    "Sci-Fi",
    "Seinen",
    "Shoujo",
    "Shounen",
    "Slice of Life",
    "Space",
    "Sports",
    "Super Power",
    "Supernatural",
    "Suspense",
    "Thriller",
    "Vampire",
    "Drama",
    "Seinen"
  ],
  "chapters": [
    {
      "number": "0",
      "title": "Chap 0",
      "url": "https://mangafire.to/read/rec22.05o5/en/chapter-0"
    }
  ],
  "fetched_at": "2026-04-27T08:48:38Z"
}