{
  "slug": "shoten.zkllp",
  "title": "Shoten",
  "cover": "https://static.mfcdn.nl/ce3b/i/4/48/48edfac9654fe025fcdda75c4d5723d9@100.jpg",
  "description": "Shoten manga, read all chapters here, the latest chapter 65 is available. Read Shoten raw, multiple language. READ NOW!!",
  "status": "Completed",
  "genres": [
    "Action",
    "Adventure",
    "Avant Garde",
    "Boys Love",
    "Comedy",
    "Demons",
    "Drama",
    "Ecchi",
    "Fantasy",
    "Girls Love",
    "Gourmet",
    "Harem",
    "Horror",
    "Isekai",
    "Iyashikei",
    "Josei",
    "Kids",
    "Magic",
    "Mahou Shoujo",
    "Martial Arts",
    "Mecha",
    "Military",
    "Music",
    "Mystery",
    "Parody",
    "Psychological",
    "Reverse Harem",
    "Romance",
    "School",
    "Sci-Fi",
    "Seinen",
    "Shoujo",
    "Shounen",
    "Slice of Life",
    "Space",
    "Sports",
    "Super Power",
    "Supernatural",
    "Suspense",
    "Thriller",
    "Vampire",
    "Boys Love",
    "Comedy",
    "Drama",
    "Shoujo"
  ],
  "chapters": [
    {
      "number": "65",
      "title": "Vol 5 -  Chap 65",
      "url": "https://mangafire.to/read/shoten.zkllp/en/chapter-65"
    },
    {
      "number": "10",
      "title": "Vol 6 -  Chap 10",
      "url": "https://mangafire.to/read/shoten.zkllp/en/chapter-10"
    },
    {
      "number": "8",
      "title": "Vol 5 -  Chap 8",
      "url": "https://mangafire.to/read/shoten.zkllp/en/chapter-8"
    },
    {
      "number": "6",
      "title": "Vol 5 -  Chap 6",
      "url": "https://mangafire.to/read/shoten.zkllp/en/chapter-6"
    },
    {
      "number": "5",
      "title": "Vol 5 -  Chap 5",
      "url": "https://mangafire.to/read/shoten.zkllp/en/chapter-5"
    },
    {
      "number": "4",
      "title": "Vol 5 -  Chap 4",
      "url": "https://mangafire.to/read/shoten.zkllp/en/chapter-4"
    },
    {
      "number": "3",
      "title": "Vol 5 -  Chap 3",
      "url": "https://mangafire.to/read/shoten.zkllp/en/chapter-3"
    },
    {
      "number": "2",
      "title": "Vol 5 -  Chap 2",
      "url": "https://mangafire.to/read/shoten.zkllp/en/chapter-2"
    },
    {
      "number": "1",
      "title": "Vol 5 -  Chap 1",
      "url": "https://mangafire.to/read/shoten.zkllp/en/chapter-1"
    }
  ],
  "fetched_at": "2026-04-27T02:26:51Z"
}