{
  "slug": "solo-fessional-solo-katsu-danshi-to-bocchi-joshi-no-koubou-sen.x160q",
  "title": "Solo-fessional: Solo Katsu Danshi to Bocchi Joshi no Koubou-sen",
  "cover": "https://static.mfcdn.nl/3aa9/i/9/95/da60f7045a1a04bbde01520eb24c793e@100.jpg",
  "description": "Solo-fessional: Solo Katsu Danshi to Bocchi Joshi no Koubou-sen manga, read all chapters here, the latest chapter 2 is available. Read Solo-fessional: Solo Katsu Danshi to Bocchi Joshi no Koubou-sen raw, multiple language. READ NOW!!",
  "status": "Completed",
  "genres": [
    "Action",
    "Adventure",
    "Avant Garde",
    "Boys Love",
    "Comedy",
    "Demons",
    "Drama",
    "Ecchi",
    "Fantasy",
    "Girls Love",
    "Gourmet",
    "Harem",
    "Horror",
    "Isekai",
    "Iyashikei",
    "Josei",
    "Kids",
    "Magic",
    "Mahou Shoujo",
    "Martial Arts",
    "Mecha",
    "Military",
    "Music",
    "Mystery",
    "Parody",
    "Psychological",
    "Reverse Harem",
    "Romance",
    "School",
    "Sci-Fi",
    "Seinen",
    "Shoujo",
    "Shounen",
    "Slice of Life",
    "Space",
    "Sports",
    "Super Power",
    "Supernatural",
    "Suspense",
    "Thriller",
    "Vampire",
    "Comedy",
    "Romance",
    "Slice of Life"
  ],
  "chapters": [
    {
      "number": "2",
      "title": "Chap 2",
      "url": "https://mangafire.to/read/solo-fessional-solo-katsu-danshi-to-bocchi-joshi-no-koubou-sen.x160q/en/chapter-2"
    },
    {
      "number": "1",
      "title": "Chap 1",
      "url": "https://mangafire.to/read/solo-fessional-solo-katsu-danshi-to-bocchi-joshi-no-koubou-sen.x160q/en/chapter-1"
    }
  ],
  "fetched_at": "2026-05-03T07:31:16Z"
}