{
  "slug": "uchuu-patrol-lulucoo.v9xo4",
  "title": "Space Patrol Luluco",
  "cover": "https://static.mfcdn.nl/485c/i/9/94/940901af398a5fc3ddd3288abf5cad75@100.jpg",
  "description": "Space Patrol Luluco manga, read all chapters here, the latest chapter 2 is available. Read Space Patrol Luluco raw, multiple language. READ NOW!!",
  "status": "Completed",
  "genres": [
    "Action",
    "Adventure",
    "Avant Garde",
    "Boys Love",
    "Comedy",
    "Demons",
    "Drama",
    "Ecchi",
    "Fantasy",
    "Girls Love",
    "Gourmet",
    "Harem",
    "Horror",
    "Isekai",
    "Iyashikei",
    "Josei",
    "Kids",
    "Magic",
    "Mahou Shoujo",
    "Martial Arts",
    "Mecha",
    "Military",
    "Music",
    "Mystery",
    "Parody",
    "Psychological",
    "Reverse Harem",
    "Romance",
    "School",
    "Sci-Fi",
    "Seinen",
    "Shoujo",
    "Shounen",
    "Slice of Life",
    "Space",
    "Sports",
    "Super Power",
    "Supernatural",
    "Suspense",
    "Thriller",
    "Vampire",
    "Comedy",
    "Sci-Fi",
    "Seinen"
  ],
  "chapters": [
    {
      "number": "2",
      "title": "Chap 2",
      "url": "https://mangafire.to/read/uchuu-patrol-lulucoo.v9xo4/en/chapter-2"
    },
    {
      "number": "1",
      "title": "Chap 1",
      "url": "https://mangafire.to/read/uchuu-patrol-lulucoo.v9xo4/en/chapter-1"
    }
  ],
  "fetched_at": "2026-04-27T08:50:22Z"
}